<?xml version="1.0" encoding="UTF-8"?><wfs:FeatureCollection xmlns:wfs="http://www.opengis.net/wfs/2.0" xmlns:xs="http://www.w3.org/2001/XMLSchema" xmlns:au="http://inspire.ec.europa.eu/schemas/au/4.0" xmlns:gml="http://www.opengis.net/gml/3.2" xmlns:gn="http://inspire.ec.europa.eu/schemas/gn/4.0" xmlns:cp="http://inspire.ec.europa.eu/schemas/cp/4.0" xmlns:xsi="http://www.w3.org/2001/XMLSchema-instance" xmlns:xlink="http://www.w3.org/1999/xlink" xmlns:base="http://inspire.ec.europa.eu/schemas/base/3.3" numberMatched="unknown" numberReturned="11" timeStamp="2021-11-15T10:37:09.792Z" xsi:schemaLocation="http://www.opengis.net/wfs/2.0 http://schemas.opengis.net/wfs/2.0/wfs.xsd http://inspire.ec.europa.eu/schemas/cp/4.0 http://inspire.ec.europa.eu/schemas/cp/4.0/CadastralParcels.xsd http://www.opengis.net/gml/3.2 http://schemas.opengis.net/gml/3.2.1/gml.xsd"><wfs:member><cp:CadastralParcel gml:id="FI_CP_CADASTRALPARCEL_217805395"><gml:identifier codeSpace="http://paikkatiedot.fi">http://paikkatiedot.fi/so/1001077/cp/CadastralParcel/217805395</gml:identifier><cp:beginLifespanVersion>2014-02-01T01:00:00Z</cp:beginLifespanVersion><cp:geometry><gml:Polygon srsDimension="2" srsName="http://www.opengis.net/gml/srs/epsg.xml#3067"><gml:exterior><gml:LinearRing><gml:posList>503145.682 7115917.707 503042.513 7115351.256 503125.547 7115218.455 503752.406 7115319.031 504264.729 7115405.33 504227.975 7115630.017 504171.671 7115976.567 503145.682 7115917.707</gml:posList></gml:LinearRing></gml:exterior></gml:Polygon></cp:geometry><cp:inspireId><base:Identifier><base:localId>217805395</base:localId><base:namespace>http://paikkatiedot.fi/so/1001077/cp/CadastralParcel/</base:namespace></base:Identifier></cp:inspireId><cp:label>205-416-15-46</cp:label><cp:nationalCadastralReference>20541600150046</cp:nationalCadastralReference><cp:referencePoint><gml:Point srsDimension="2" srsName="http://www.opengis.net/gml/srs/epsg.xml#3067"><gml:pos>503552.644 7115687.825</gml:pos></gml:Point></cp:referencePoint><cp:basicPropertyUnit xlink:href="FI_CP_BASICPROPERTYUNIT_20541600150046"/></cp:CadastralParcel></wfs:member><wfs:member><cp:CadastralParcel gml:id="FI_CP_CADASTRALPARCEL_225786095"><gml:identifier codeSpace="http://paikkatiedot.fi">http://paikkatiedot.fi/so/1001077/cp/CadastralParcel/225786095</gml:identifier><cp:beginLifespanVersion>2009-07-11T00:00:00Z</cp:beginLifespanVersion><cp:geometry><gml:Polygon srsDimension="2" srsName="http://www.opengis.net/gml/srs/epsg.xml#3067"><gml:exterior><gml:LinearRing><gml:posList>502591.519 7115491.714 502496.782 7115507.455 502364.672 7115527.873 502364.43 7115527.912 502605.847 7115171.977 502731.686 7115148.789 502930.262 7115112.119 503124.926 7115076.268 503223.202 7115058.111 503226.134 7115057.599 503125.547 7115218.455 503042.513 7115351.256 502953.847 7115493.968 502852.832 7115655.196 502591.519 7115491.714</gml:posList></gml:LinearRing></gml:exterior></gml:Polygon></cp:geometry><cp:inspireId><base:Identifier><base:localId>225786095</base:localId><base:namespace>http://paikkatiedot.fi/so/1001077/cp/CadastralParcel/</base:namespace></base:Identifier></cp:inspireId><cp:label>205-416-12-70</cp:label><cp:nationalCadastralReference>20541600120070</cp:nationalCadastralReference><cp:referencePoint><gml:Point srsDimension="2" srsName="http://www.opengis.net/gml/srs/epsg.xml#3067"><gml:pos>502772.529 7115303.569</gml:pos></gml:Point></cp:referencePoint><cp:basicPropertyUnit xlink:href="FI_CP_BASICPROPERTYUNIT_20541600120070"/></cp:CadastralParcel></wfs:member><wfs:member><cp:CadastralParcel gml:id="FI_CP_CADASTRALPARCEL_66938232"><gml:identifier codeSpace="http://paikkatiedot.fi">http://paikkatiedot.fi/so/1001077/cp/CadastralParcel/66938232</gml:identifier><cp:beginLifespanVersion>2009-07-07T00:00:00Z</cp:beginLifespanVersion><cp:geometry><gml:Polygon srsDimension="2" srsName="http://www.opengis.net/gml/srs/epsg.xml#3067"><gml:exterior><gml:LinearRing><gml:posList>502953.847 7115493.968 503042.513 7115351.256 503145.682 7115917.707 503163.641 7116016.309 503051.727 7116031.492 502953.847 7115493.968</gml:posList></gml:LinearRing></gml:exterior></gml:Polygon></cp:geometry><cp:inspireId><base:Identifier><base:localId>66938232</base:localId><base:namespace>http://paikkatiedot.fi/so/1001077/cp/CadastralParcel/</base:namespace></base:Identifier></cp:inspireId><cp:label>205-416-15-24</cp:label><cp:nationalCadastralReference>20541600150024</cp:nationalCadastralReference><cp:referencePoint><gml:Point srsDimension="2" srsName="http://www.opengis.net/gml/srs/epsg.xml#3067"><gml:pos>503003.823 7115685.814</gml:pos></gml:Point></cp:referencePoint><cp:basicPropertyUnit xlink:href="FI_CP_BASICPROPERTYUNIT_20541600150024"/></cp:CadastralParcel></wfs:member><wfs:member><cp:CadastralParcel gml:id="FI_CP_CADASTRALPARCEL_66938233"><gml:identifier codeSpace="http://paikkatiedot.fi">http://paikkatiedot.fi/so/1001077/cp/CadastralParcel/66938233</gml:identifier><cp:beginLifespanVersion>2009-07-07T00:00:00Z</cp:beginLifespanVersion><cp:geometry><gml:Polygon srsDimension="2" srsName="http://www.opengis.net/gml/srs/epsg.xml#3067"><gml:exterior><gml:LinearRing><gml:posList>502852.832 7115655.196 502953.847 7115493.968 503051.727 7116031.492 503047.767 7116032.044 502880.277 7116050.979 502869 7115924.861 502852.832 7115655.196</gml:posList></gml:LinearRing></gml:exterior></gml:Polygon></cp:geometry><cp:inspireId><base:Identifier><base:localId>66938233</base:localId><base:namespace>http://paikkatiedot.fi/so/1001077/cp/CadastralParcel/</base:namespace></base:Identifier></cp:inspireId><cp:label>205-416-15-22</cp:label><cp:nationalCadastralReference>20541600150022</cp:nationalCadastralReference><cp:referencePoint><gml:Point srsDimension="2" srsName="http://www.opengis.net/gml/srs/epsg.xml#3067"><gml:pos>502876.586 7115813.701</gml:pos></gml:Point></cp:referencePoint><cp:basicPropertyUnit xlink:href="FI_CP_BASICPROPERTYUNIT_20541600150022"/></cp:CadastralParcel></wfs:member><wfs:member><cp:CadastralParcel gml:id="FI_CP_CADASTRALPARCEL_66938245"><gml:identifier codeSpace="http://paikkatiedot.fi">http://paikkatiedot.fi/so/1001077/cp/CadastralParcel/66938245</gml:identifier><cp:beginLifespanVersion>2012-02-02T01:00:00Z</cp:beginLifespanVersion><cp:geometry><gml:Polygon srsDimension="2" srsName="http://www.opengis.net/gml/srs/epsg.xml#3067"><gml:exterior><gml:LinearRing><gml:posList>502776.653 7115884.2 502792.122 7115882.447 502790.976 7115750.18 502832.509 7115753.71 502844.596 7115926.92 502865.539 7115925.05 502869 7115924.861 502880.277 7116050.979 502790.773 7116080.945 502776.653 7115884.2</gml:posList></gml:LinearRing></gml:exterior></gml:Polygon></cp:geometry><cp:inspireId><base:Identifier><base:localId>66938245</base:localId><base:namespace>http://paikkatiedot.fi/so/1001077/cp/CadastralParcel/</base:namespace></base:Identifier></cp:inspireId><cp:label>205-403-4-16</cp:label><cp:nationalCadastralReference>20540300040016</cp:nationalCadastralReference><cp:referencePoint><gml:Point srsDimension="2" srsName="http://www.opengis.net/gml/srs/epsg.xml#3067"><gml:pos>502808.776 7115955.414</gml:pos></gml:Point></cp:referencePoint><cp:basicPropertyUnit xlink:href="FI_CP_BASICPROPERTYUNIT_20540300040016"/></cp:CadastralParcel></wfs:member><wfs:member><cp:CadastralParcel gml:id="FI_CP_CADASTRALPARCEL_66938246"><gml:identifier codeSpace="http://paikkatiedot.fi">http://paikkatiedot.fi/so/1001077/cp/CadastralParcel/66938246</gml:identifier><cp:beginLifespanVersion>2012-02-02T01:00:00Z</cp:beginLifespanVersion><cp:geometry><gml:Polygon srsDimension="2" srsName="http://www.opengis.net/gml/srs/epsg.xml#3067"><gml:exterior><gml:LinearRing><gml:posList>502491.146 7115979.86 502469.264 7115723.383 502508.951 7115726.28 502790.976 7115750.18 502792.122 7115882.447 502776.653 7115884.2 502790.773 7116080.945 502491.146 7115979.86</gml:posList></gml:LinearRing></gml:exterior></gml:Polygon></cp:geometry><cp:inspireId><base:Identifier><base:localId>66938246</base:localId><base:namespace>http://paikkatiedot.fi/so/1001077/cp/CadastralParcel/</base:namespace></base:Identifier></cp:inspireId><cp:label>205-403-4-15</cp:label><cp:nationalCadastralReference>20540300040015</cp:nationalCadastralReference><cp:referencePoint><gml:Point srsDimension="2" srsName="http://www.opengis.net/gml/srs/epsg.xml#3067"><gml:pos>502593.779 7115905.201</gml:pos></gml:Point></cp:referencePoint><cp:basicPropertyUnit xlink:href="FI_CP_BASICPROPERTYUNIT_20540300040015"/></cp:CadastralParcel></wfs:member><wfs:member><cp:CadastralParcel gml:id="FI_CP_CADASTRALPARCEL_66938247"><gml:identifier codeSpace="http://paikkatiedot.fi">http://paikkatiedot.fi/so/1001077/cp/CadastralParcel/66938247</gml:identifier><cp:beginLifespanVersion>2012-02-02T01:00:00Z</cp:beginLifespanVersion><cp:geometry><gml:Polygon srsDimension="2" srsName="http://www.opengis.net/gml/srs/epsg.xml#3067"><gml:exterior><gml:LinearRing><gml:posList>502064.247 7115726.839 502068.75 7115719.135 502223.963 7115552.736 502364.43 7115527.912 502364.672 7115527.873 502496.782 7115507.455 502508.951 7115726.28 502469.264 7115723.383 502491.146 7115979.86 502409.914 7115952.454 502064.247 7115726.839</gml:posList></gml:LinearRing></gml:exterior></gml:Polygon></cp:geometry><cp:inspireId><base:Identifier><base:localId>66938247</base:localId><base:namespace>http://paikkatiedot.fi/so/1001077/cp/CadastralParcel/</base:namespace></base:Identifier></cp:inspireId><cp:label>205-403-4-16</cp:label><cp:nationalCadastralReference>20540300040016</cp:nationalCadastralReference><cp:referencePoint><gml:Point srsDimension="2" srsName="http://www.opengis.net/gml/srs/epsg.xml#3067"><gml:pos>502267.38 7115767.203</gml:pos></gml:Point></cp:referencePoint><cp:basicPropertyUnit xlink:href="FI_CP_BASICPROPERTYUNIT_20540300040016"/></cp:CadastralParcel></wfs:member><wfs:member><cp:CadastralParcel gml:id="FI_CP_CADASTRALPARCEL_66938248"><gml:identifier codeSpace="http://paikkatiedot.fi">http://paikkatiedot.fi/so/1001077/cp/CadastralParcel/66938248</gml:identifier><cp:beginLifespanVersion>2012-02-02T01:00:00Z</cp:beginLifespanVersion><cp:geometry><gml:Polygon srsDimension="2" srsName="http://www.opengis.net/gml/srs/epsg.xml#3067"><gml:exterior><gml:LinearRing><gml:posList>502508.951 7115726.28 502496.782 7115507.455 502591.519 7115491.714 502852.832 7115655.196 502869 7115924.861 502865.539 7115925.05 502844.596 7115926.92 502832.509 7115753.71 502790.976 7115750.18 502508.951 7115726.28</gml:posList></gml:LinearRing></gml:exterior></gml:Polygon></cp:geometry><cp:inspireId><base:Identifier><base:localId>66938248</base:localId><base:namespace>http://paikkatiedot.fi/so/1001077/cp/CadastralParcel/</base:namespace></base:Identifier></cp:inspireId><cp:label>205-403-4-14</cp:label><cp:nationalCadastralReference>20540300040014</cp:nationalCadastralReference><cp:referencePoint><gml:Point srsDimension="2" srsName="http://www.opengis.net/gml/srs/epsg.xml#3067"><gml:pos>502615.071 7115656.133</gml:pos></gml:Point></cp:referencePoint><cp:basicPropertyUnit xlink:href="FI_CP_BASICPROPERTYUNIT_20540300040014"/></cp:CadastralParcel></wfs:member><wfs:member><cp:CadastralParcel gml:id="FI_CP_CADASTRALPARCEL_66938254"><gml:identifier codeSpace="http://paikkatiedot.fi">http://paikkatiedot.fi/so/1001077/cp/CadastralParcel/66938254</gml:identifier><cp:beginLifespanVersion>2014-01-09T01:00:00Z</cp:beginLifespanVersion><cp:geometry><gml:Polygon srsDimension="2" srsName="http://www.opengis.net/gml/srs/epsg.xml#3067"><gml:exterior><gml:LinearRing><gml:posList>503035.382 7114539.966 503182.603 7114322.985 503413.079 7113981.879 503754.64 7114212.381 503685.019 7114321.868 503226.134 7115057.599 503223.202 7115058.111 503124.926 7115076.268 502930.262 7115112.119 502731.686 7115148.789 502605.847 7115171.977 503035.382 7114539.966</gml:posList></gml:LinearRing></gml:exterior></gml:Polygon></cp:geometry><cp:inspireId><base:Identifier><base:localId>66938254</base:localId><base:namespace>http://paikkatiedot.fi/so/1001077/cp/CadastralParcel/</base:namespace></base:Identifier></cp:inspireId><cp:label>205-416-12-22</cp:label><cp:nationalCadastralReference>20541600120022</cp:nationalCadastralReference><cp:referencePoint><gml:Point srsDimension="2" srsName="http://www.opengis.net/gml/srs/epsg.xml#3067"><gml:pos>503138.313 7114685.315</gml:pos></gml:Point></cp:referencePoint><cp:basicPropertyUnit xlink:href="FI_CP_BASICPROPERTYUNIT_20541600120022"/></cp:CadastralParcel></wfs:member><wfs:member><cp:CadastralParcel gml:id="FI_CP_CADASTRALPARCEL_66938256"><gml:identifier codeSpace="http://paikkatiedot.fi">http://paikkatiedot.fi/so/1001077/cp/CadastralParcel/66938256</gml:identifier><cp:beginLifespanVersion>2014-01-09T01:00:00Z</cp:beginLifespanVersion><cp:geometry><gml:Polygon srsDimension="2" srsName="http://www.opengis.net/gml/srs/epsg.xml#3067"><gml:exterior><gml:LinearRing><gml:posList>502728.014 7114607.449 502726.309 7114606.403 502556.148 7114501.961 502602.714 7114422.872 502733.2 7114277.933 503035.382 7114539.966 502605.847 7115171.977 502604.197 7115170.85 502440.588 7115059.089 502728.014 7114607.449</gml:posList></gml:LinearRing></gml:exterior></gml:Polygon></cp:geometry><cp:inspireId><base:Identifier><base:localId>66938256</base:localId><base:namespace>http://paikkatiedot.fi/so/1001077/cp/CadastralParcel/</base:namespace></base:Identifier></cp:inspireId><cp:label>205-416-12-47</cp:label><cp:nationalCadastralReference>20541600120047</cp:nationalCadastralReference><cp:referencePoint><gml:Point srsDimension="2" srsName="http://www.opengis.net/gml/srs/epsg.xml#3067"><gml:pos>502631.84 7114893.675</gml:pos></gml:Point></cp:referencePoint><cp:basicPropertyUnit xlink:href="FI_CP_BASICPROPERTYUNIT_20541600120047"/></cp:CadastralParcel></wfs:member><wfs:member><cp:CadastralParcel gml:id="FI_CP_CADASTRALPARCEL_66938257"><gml:identifier codeSpace="http://paikkatiedot.fi">http://paikkatiedot.fi/so/1001077/cp/CadastralParcel/66938257</gml:identifier><cp:beginLifespanVersion>2014-01-09T01:00:00Z</cp:beginLifespanVersion><cp:geometry><gml:Polygon srsDimension="2" srsName="http://www.opengis.net/gml/srs/epsg.xml#3067"><gml:exterior><gml:LinearRing><gml:posList>502472.327 7114638.051 502556.148 7114501.961 502726.309 7114606.403 502728.014 7114607.449 502440.588 7115059.089 502604.197 7115170.85 502605.847 7115171.977 502364.43 7115527.912 502223.963 7115552.736 502066.48 7115297.367 502063.594 7115292.688 502472.327 7114638.051</gml:posList></gml:LinearRing></gml:exterior></gml:Polygon></cp:geometry><cp:inspireId><base:Identifier><base:localId>66938257</base:localId><base:namespace>http://paikkatiedot.fi/so/1001077/cp/CadastralParcel/</base:namespace></base:Identifier></cp:inspireId><cp:label>205-416-12-46</cp:label><cp:nationalCadastralReference>20541600120046</cp:nationalCadastralReference><cp:referencePoint><gml:Point srsDimension="2" srsName="http://www.opengis.net/gml/srs/epsg.xml#3067"><gml:pos>502211.573 7115176.862</gml:pos></gml:Point></cp:referencePoint><cp:basicPropertyUnit xlink:href="FI_CP_BASICPROPERTYUNIT_20541600120046"/></cp:CadastralParcel></wfs:member></wfs:FeatureCollection>