<?xml version="1.0" encoding="UTF-8"?><wfs:FeatureCollection xmlns:wfs="http://www.opengis.net/wfs/2.0" xmlns:xs="http://www.w3.org/2001/XMLSchema" xmlns:au="http://inspire.ec.europa.eu/schemas/au/4.0" xmlns:gml="http://www.opengis.net/gml/3.2" xmlns:gn="http://inspire.ec.europa.eu/schemas/gn/4.0" xmlns:cp="http://inspire.ec.europa.eu/schemas/cp/4.0" xmlns:xsi="http://www.w3.org/2001/XMLSchema-instance" xmlns:xlink="http://www.w3.org/1999/xlink" xmlns:base="http://inspire.ec.europa.eu/schemas/base/3.3" numberMatched="unknown" numberReturned="2" timeStamp="2021-11-15T09:16:30.035Z" xsi:schemaLocation="http://www.opengis.net/wfs/2.0 http://schemas.opengis.net/wfs/2.0/wfs.xsd http://inspire.ec.europa.eu/schemas/cp/4.0 http://inspire.ec.europa.eu/schemas/cp/4.0/CadastralParcels.xsd http://www.opengis.net/gml/3.2 http://schemas.opengis.net/gml/3.2.1/gml.xsd"><wfs:member><cp:CadastralParcel gml:id="FI_CP_CADASTRALPARCEL_57619618"><gml:identifier codeSpace="http://paikkatiedot.fi">http://paikkatiedot.fi/so/1001077/cp/CadastralParcel/57619618</gml:identifier><cp:beginLifespanVersion>2014-11-28T01:00:00Z</cp:beginLifespanVersion><cp:geometry><gml:Polygon srsDimension="2" srsName="http://www.opengis.net/gml/srs/epsg.xml#3067"><gml:exterior><gml:LinearRing><gml:posList>603715.017 7293123.494 603710.311 7293121.195 603705.118 7293121.458 603695.149 7293121.857 603688.545 7293121.626 603674.375 7293120.432 603668.468 7293120.753 603661.912 7293122.619 603655.856 7293125.22 603650.824 7293128.478 603649.229 7293129.173 603641.905 7293130.13 603634.963 7293129.098 603629.948 7293129.018 603623.23 7293132.154 603607.34 7293145.411 603598.18 7293153.87 603593.278 7293161.984 603593.87 7293166.753 603596.586 7293171.409 603598.733 7293176.392 603597.571 7293182.343 603594.204 7293189.01 603593.627 7293194.983 603592.662 7293198.011 603587.708 7293200.642 603575.577 7293199.421 603567.828 7293200.18 603563.597 7293204.586 603560.77 7293209.229 603558.06 7293210.934 603553.46 7293210.895 603544.168 7293210.796 603538.842 7293212.108 603534.323 7293216.391 603530.368 7293219.625 603525.859 7293221.818 603521.124 7293223.588 603512.618 7293227.374 603501.078 7293241.208 603499.285 7293244.1 603491.703 7293251.307 603477.158 7293261.147 603468.448 7293269.518 603446.468 7293267.172 603446.669 7293266.287 603524.003 7292934.706 603561.908 7292833.259 603612.226 7292754.803 603669.37 7292691.638 603740.214 7292638.784 603933.36 7292530.241 604195.675 7292380.444 604289.132 7292303.189 604572.826 7292143.684 604671.3 7292317.836 604853.639 7292233.375 604763.228 7292060.43 604759.059 7292052.457 604905.585 7291974.276 604910.399 7291981.877 605548.098 7292988.799 605565.846 7293016.71 605564.874 7293020.178 605564.781 7293020.553 605564.342 7293022.503 605563.907 7293024.455 605563.397 7293026.388 605562.737 7293028.274 605562.523 7293028.76 605561.652 7293030.559 605560.814 7293032.373 605560.195 7293034.272 605560.001 7293035.666 605560.098 7293037.659 605560.646 7293039.576 605561.488 7293041.175 605562.45 7293042.927 605562.982 7293044.413 605563.474 7293046.35 605564.022 7293048.272 605564.852 7293050.167 605565.818 7293051.917 605566.796 7293053.661 605567.499 7293055.068 605568.378 7293056.864 605569.387 7293058.588 605570.654 7293060.13 605571.987 7293061.211 605573.739 7293062.17 605575.608 7293062.873 605576.006 7293062.989 605577.953 7293063.44 605579.926 7293063.76 605581.903 7293064.062 605583.998 7293064.493 605585.891 7293065.125 605587.518 7293066.268 605588.401 7293067.455 605589.38 7293069.198 605590.481 7293070.862 605591.282 7293071.613 605592.999 7293072.625 605594.881 7293073.297 605596.79 7293073.894 605597.418 7293074.115 605599.288 7293074.823 605601.141 7293075.573 605602.506 7293076.145 605604.313 7293076.997 605605.941 7293078.15 605607.146 7293079.413 605608.573 7293080.81 605609.313 7293081.302 605611.035 7293082.318 605612.48 7293083.675 605612.62 7293083.944 605612.923 7293085.899 605612.49 7293087.842 605612.016 7293088.827 605610.788 7293090.398 605609.379 7293091.817 605608.061 7293093.109 605606.666 7293094.54 605605.319 7293096.018 605604.039 7293097.553 605603.583 7293098.137 605602.36 7293099.718 605601.05 7293101.227 605599.527 7293102.518 605597.654 7293103.498 605595.761 7293104.138 605593.822 7293104.624 605591.876 7293105.079 605589.95 7293105.618 605587.996 7293106.406 605584.379 7293108.109 605582.533 7293108.877 605582.155 7293109.006 605580.228 7293109.535 605578.269 7293109.931 605576.296 7293110.247 605572.353 7293110.913 605571.809 7293111.033 605569.872 7293111.53 605560.349 7293114.566 605558.734 7293115 605556.785 7293115.444 605554.817 7293115.801 605552.835 7293116.058 605551.512 7293116.175 605549.516 7293116.279 605547.516 7293116.313 605545.517 7293116.291 605541.52 7293116.211 605540.286 7293116.199 605534.29 7293116.302 605532.294 7293116.408 605530.3 7293116.559 605528.312 7293116.763 605526.33 7293117.024 605525.281 7293117.186 605519.365 7293118.176 605517.377 7293118.384 605516.29 7293118.449 605514.295 7293118.567 605508.322 7293119.107 605506.349 7293119.428 605504.302 7293120.009 605500.504 7293121.261 605498.582 7293121.808 605496.624 7293122.202 605492.404 7293122.473 605490.417 7293122.688 605488.486 7293123.191 605486.667 7293124.147 605485.041 7293125.31 605484.351 7293125.832 605482.71 7293126.971 605480.937 7293127.887 605479.981 7293128.129 605477.99 7293128.223 605476.008 7293127.962 605474.05 7293127.558 605473.641 7293127.461 605471.702 7293126.975 605467.854 7293125.892 605467.299 7293125.722 605459.686 7293123.274 605459.028 7293123.066 605457.113 7293122.494 605455.182 7293121.976 605453.23 7293121.544 605451.249 7293121.281 605449.252 7293121.214 605449.172 7293121.219 605447.493 7293121.33 605445.524 7293121.668 605443.6 7293122.212 605442.729 7293122.536 605439.045 7293124.091 605437.171 7293124.784 605435.442 7293125.244 605433.522 7293125.805 605431.654 7293126.508 605431.145 7293126.797 605429.422 7293127.808 605427.499 7293128.282 605427.007 7293128.229 605425.069 7293127.745 605423.111 7293127.643 605422.302 7293129.405 605422.494 7293131.386 605422.74 7293132.213 605423.037 7293134.13 605422.102 7293134.186 605420.136 7293134.506 605419.223 7293135.272 605418.885 7293137.128 605420.184 7293137.658 605422.089 7293138.183 605422.215 7293139.423 605421.18 7293141.114 605419.793 7293141.785 605419.478 7293141.545 605418.255 7293139.967 605417.045 7293141.567 605415.661 7293142.919 605415.293 7293142.891 605413.53 7293141.96 605411.756 7293142.217 605411.478 7293143.436 605412.044 7293145.352 605412.34 7293146.252 605412.806 7293148.195 605412.832 7293150.189 605412.448 7293151.887 605411.426 7293153.583 605409.896 7293154.308 605407.926 7293154.633 605405.93 7293154.747 605404.375 7293154.858 605402.405 7293155.188 605400.516 7293155.833 605398.692 7293156.834 605396.981 7293157.87 605395.197 7293158.766 605393.306 7293159.296 605391.32 7293159.508 605390.34 7293159.517 605388.343 7293159.429 605386.348 7293159.307 605384.349 7293159.257 605382.902 7293159.341 605380.924 7293159.628 605378.979 7293160.093 605377.073 7293160.692 605375.208 7293161.411 605373.735 7293162.067 605371.936 7293162.941 605366.555 7293165.585 605365.8 7293165.917 605363.949 7293166.67 605362.068 7293167.35 605360.167 7293167.967 605356.322 7293169.062 605346.445 7293171.591 605344.332 7293172.274 605342.472 7293173.005 605340.691 7293173.91 605339.022 7293175.009 605337.371 7293176.451 605336.218 7293178.072 605336.033 7293180.029 605336.467 7293181.22 605337.045 7293183.11 605336.62 7293183.693 605334.717 7293184.252 605332.741 7293184.558 605330.891 7293185.059 605327.138 7293186.439 605325.004 7293187.011 605319.133 7293188.233 605317.346 7293188.677 605309.652 7293190.856 605309.261 7293190.951 605307.308 7293191.384 605305.346 7293191.762 605301.413 7293192.482 605299.736 7293192.808 605291.95 7293194.624 605291.453 7293194.759 605289.541 7293195.342 605287.675 7293196.06 605285.949 7293197.059 605284.513 7293198.442 605283.687 7293199.671 605282.976 7293201.533 605282.966 7293203.515 605284.03 7293205.523 605285.325 7293207.046 605286.625 7293208.679 605287.447 7293210.487 605287.563 7293211.83 605287.089 7293213.76 605286.355 7293214.916 605284.846 7293216.215 605283.039 7293217.059 605281.101 7293217.501 605279.157 7293217.96 605277.619 7293218.69 605275.886 7293219.686 605275.486 7293219.912 605273.697 7293220.802 605271.811 7293221.462 605270.644 7293221.707 605268.664 7293221.978 605266.679 7293222.216 605264.713 7293222.567 605264.013 7293222.761 605262.145 7293223.468 605260.354 7293224.36 605258.597 7293225.311 605256.904 7293226.258 605255.167 7293227.248 605253.437 7293228.25 605252.79 7293228.627 605251.007 7293229.528 605249.051 7293229.774 605248.108 7293229.492 605246.193 7293228.951 605244.336 7293229.549 605242.99 7293230.998 605242.531 7293232.926 605242.209 7293234.896 605241.82 7293235.848 605240.365 7293237.074 605239.018 7293236.625 605238 7293236.457 605236.072 7293236.923 605234.245 7293237.734 605233.408 7293238.045 605231.487 7293238.596 605230.348 7293238.934 605228.501 7293239.693 605227.381 7293241.253 605227.369 7293241.672 605228.183 7293243.445 605228.609 7293243.679 605230.577 7293243.556 605232.527 7293243.121 605233.4 7293243.097 605235.231 7293243.78 605235.643 7293244.653 605235.363 7293246.617 605234.66 7293248.486 605233.873 7293250.114 605232.804 7293251.801 605231.362 7293253.175 605230.432 7293253.729 605228.553 7293254.398 605226.6 7293254.817 605224.633 7293255.176 605222.711 7293255.562 605220.783 7293256.091 605218.955 7293256.894 605218.346 7293257.276 605216.748 7293258.475 605213.672 7293261.03 605212.15 7293262.118 605210.425 7293263.126 605208.61 7293263.966 605206.724 7293264.625 605205.909 7293264.849 605203.947 7293265.229 605201.955 7293265.366 605199.967 7293265.183 605199.273 7293265.033 605197.356 7293264.471 605195.441 7293263.898 605194.512 7293263.687 605192.534 7293263.406 605190.537 7293263.332 605188.539 7293263.401 605186.548 7293263.577 605185.026 7293263.779 605183.062 7293264.151 605181.143 7293264.709 605179.337 7293265.56 605178.356 7293266.196 605176.811 7293267.464 605175.404 7293268.884 605174.031 7293270.337 605169.767 7293274.649 605168.433 7293276.138 605167.188 7293277.702 605166.52 7293278.656 605165.484 7293280.365 605164.59 7293282.152 605163.847 7293284.008 605163.276 7293285.923 605162.891 7293287.884 605162.7 7293289.813 605162.59 7293291.809 605162.482 7293293.806 605162.285 7293295.795 605161.837 7293297.941 605161.179 7293299.826 605160.217 7293301.575 605159.095 7293302.972 605157.633 7293304.333 605156.076 7293305.587 605155.231 7293306.227 605153.61 7293307.398 605151.95 7293308.512 605150.238 7293309.542 605149.482 7293309.958 605142.314 7293313.504 605141.587 7293313.892 605139.851 7293314.883 605138.152 7293315.938 605136.491 7293317.049 605134.865 7293318.213 605133.277 7293319.427 605132.74 7293319.857 605129.594 7293322.325 605127.905 7293323.392 605126.123 7293324.297 605124.472 7293324.974 605122.605 7293325.69 605120.775 7293326.491 605119.172 7293327.671 605118.397 7293329.467 605118.671 7293331.273 605118.902 7293333.252 605118.777 7293333.845 605117.686 7293335.499 605116.734 7293336.361 605116.206 7293336.84 605115.397 7293337.483 605112.247 7293339.946 605110.738 7293341.256 605109.337 7293342.682 605107.992 7293344.37 605106.821 7293345.991 605105.63 7293347.596 605104.734 7293348.677 605103.349 7293350.118 605101.803 7293351.384 605100.064 7293352.474 605098.305 7293353.423 605096.562 7293354.4 605095.888 7293354.826 605094.249 7293355.972 605092.658 7293357.182 605089.48 7293359.608 605087.83 7293360.736 605086.787 7293361.356 605085.015 7293362.28 605083.181 7293363.075 605081.317 7293363.796 605077.563 7293365.173 605075.475 7293365.936 605069.914 7293368.183 605068.922 7293368.635 605067.128 7293369.518 605065.378 7293370.485 605063.696 7293371.564 605063.414 7293371.763 605061.8 7293372.943 605060.156 7293374.08 605058.728 7293374.906 605057.006 7293375.922 605055.471 7293377.197 605054.779 7293378.065 605053.932 7293379.865 605053.731 7293381.955 605053.78 7293383.953 605053.632 7293385.944 605053.374 7293386.949 605052.787 7293388.86 605052.354 7293390.805 605053.072 7293392.575 605053.633 7293392.864 605055.438 7293393.701 605055.646 7293395.078 605054.639 7293396.797 605053.497 7293398.437 605052.893 7293399.403 605052.057 7293401.215 605051.808 7293403.186 605052.131 7293404.809 605052.642 7293406.742 605052.989 7293408.539 605053.714 7293410.387 605054.91 7293411.325 605056.784 7293412.02 605058.586 7293413.206 605058.453 7293414.049 605060.156 7293415.159 605062.109 7293415.577 605062.762 7293415.886 605064.016 7293417.402 605064.703 7293419.277 605065.217 7293420.915 605065.959 7293422.77 605067.334 7293424.179 605067.659 7293424.323 605071.549 7293425.213 605072.162 7293425.555 605073.517 7293427.008 605074.468 7293428.763 605074.852 7293429.691 605075.458 7293431.595 605075.837 7293433.557 605075.989 7293435.549 605075.976 7293436.804 605075.803 7293438.795 605075.488 7293440.769 605075.088 7293442.729 605074.975 7293443.228 605074.496 7293445.17 605073.955 7293447.094 605073.339 7293448.995 605073.176 7293449.455 605072.437 7293451.312 605071.546 7293453.099 605070.404 7293454.739 605069.785 7293455.428 605068.28 7293456.741 605066.601 7293457.822 605064.806 7293458.703 605063.178 7293459.324 605061.323 7293460.069 605059.512 7293460.916 605058.214 7293461.805 605056.699 7293463.107 605055.214 7293464.447 605053.842 7293465.597 605052.269 7293466.832 605049.105 7293469.275 605047.659 7293470.425 605046.048 7293471.608 605044.332 7293472.627 605043.001 7293473.105 605039.114 7293474.04 605037.2 7293474.615 605035.835 7293475.235 605034.038 7293476.11 605032.151 7293476.756 605030.796 7293476.887 605028.813 7293476.662 605026.877 7293476.165 605025.266 7293475.586 605023.493 7293474.671 605022.006 7293473.345 605020.873 7293471.717 605019.764 7293470.054 605018.238 7293468.802 605017.569 7293468.668 605015.593 7293468.903 605013.646 7293469.357 605012.649 7293469.497 605008.659 7293469.738 605006.74 7293470.065 605004.771 7293470.411 605002.776 7293470.487 605002.454 7293470.451 605000.495 7293470.056 604998.54 7293469.64 604996.551 7293469.622 604995.567 7293469.959 604993.941 7293471.111 604992.476 7293472.47 604991.904 7293472.959 604990.359 7293474.228 604988.743 7293475.403 604986.976 7293476.334 604986.232 7293476.62 604982.429 7293477.852 604978.758 7293479.563 604976.659 7293480.365 604974.924 7293481.347 604974.533 7293481.67 604973.727 7293483.387 604973.984 7293483.961 604975.008 7293485.677 604973.308 7293486.097 604971.838 7293486.113 604969.852 7293486.293 604968.463 7293486.918 604967.365 7293488.527 604967.283 7293489.015 604967.035 7293490.999 604966.505 7293490.713 604964.667 7293489.951 604964.17 7293490.309 604963.184 7293491.02 604963.194 7293492.973 604963.766 7293494.887 604964.085 7293496.104 604964.779 7293497.968 604965.674 7293498.977 604967.015 7293500.453 604967.26 7293500.916 604967.605 7293502.867 604967.1 7293504.783 604966.183 7293505.925 604964.58 7293507.117 604963.44 7293507.79 604961.757 7293508.869 604960.189 7293510.104 604958.928 7293511.65 604957.995 7293513.501 604957.171 7293515.322 604956.088 7293516.997 604954.784 7293518.06 604952.961 7293518.875 604951.028 7293519.378 604950.694 7293519.439 604948.711 7293519.686 604946.717 7293519.826 604945.866 7293520.84 604944.977 7293522.604 604944.949 7293523.317 604945.277 7293525.286 604945.45 7293527.269 604945.216 7293527.967 604944.239 7293529.709 604943.907 7293530.249 604942.727 7293531.86 604941.076 7293532.881 604940.343 7293532.719 604938.458 7293532.065 604937.564 7293532.824 604937.173 7293534.777 604936.982 7293536.768 604936.614 7293538.729 604936.08 7293539.829 604934.775 7293541.341 604934.529 7293542.496 604934.017 7293544.428 604933.135 7293546.216 604932.794 7293546.673 604931.328 7293548.024 604929.61 7293549.043 604927.79 7293549.869 604925.721 7293550.626 604920.008 7293552.449 604918.128 7293553.126 604917.309 7293553.463 604915.533 7293554.394 604913.69 7293555.162 604913.354 7293555.228 604911.402 7293555.658 604909.478 7293556.198 604907.662 7293557.018 604906.193 7293558.361 604906.012 7293558.612 604905.026 7293560.349 604903.975 7293562.046 604903.578 7293562.482 604901.951 7293563.628 604900.075 7293564.307 604898.106 7293564.639 604897.303 7293564.686 604895.306 7293564.631 604893.325 7293564.369 604889.4 7293563.604 604888.566 7293563.464 604886.585 7293563.202 604884.592 7293563.043 604882.594 7293562.994 604880.596 7293563.046 604880.018 7293563.079 604878.023 7293563.237 604876.026 7293563.269 604874.066 7293562.905 604872.376 7293561.867 604871.871 7293561.289 604870.855 7293559.569 604870.205 7293558.847 604868.826 7293557.399 604867.364 7293556.037 604865.71 7293554.924 604863.826 7293554.267 604862.022 7293554.02 604860.082 7293553.572 604859.404 7293553.19 604858.025 7293551.756 604856.918 7293550.092 604855.952 7293548.439 604855.032 7293546.663 604854.301 7293544.805 604853.89 7293542.851 604853.817 7293541.223 604853.872 7293539.224 604853.928 7293537.226 604853.829 7293535.231 604853.353 7293533.297 604852.275 7293531.598 604850.797 7293530.258 604849.172 7293529.093 604847.497 7293528.003 604845.702 7293528.36 604844.946 7293528.255 604843.136 7293527.423 604841.402 7293526.429 604840.936 7293526.225 604839.008 7293525.723 604837.011 7293525.623 604835.012 7293525.638 604833.029 7293525.559 604831.277 7293524.702 604829.972 7293523.053 604829.318 7293523.011 604827.388 7293523.52 604825.382 7293523.653 604823.501 7293523.006 604821.915 7293521.8 604820.88 7293520.618 604819.386 7293519.309 604817.731 7293519.007 604815.733 7293519.001 604813.977 7293518.922 604812.002 7293518.612 604810.848 7293518.324 604809.018 7293517.535 604807.574 7293516.519 604805.74 7293515.81 604805.126 7293515.91 604803.172 7293516.263 604802.662 7293516.108 604800.817 7293515.371 604799.694 7293515.903 604798.655 7293517.592 604798.361 7293518.873 604797.965 7293520.829 604797.464 7293521.704 604796.271 7293523.308 604795.334 7293525.145 604794.372 7293526.893 604793.978 7293527.363 604792.391 7293528.566 604791.53 7293528.949 604789.581 7293529.366 604787.583 7293529.406 604785.586 7293529.324 604784.251 7293529.246 604782.253 7293529.151 604780.255 7293529.108 604779.546 7293529.107 604777.546 7293529.077 604777.003 7293529.041 604775.012 7293528.855 604773.017 7293528.734 604771.986 7293528.746 604769.987 7293528.735 604768.1 7293528.138 604767.336 7293527.424 604766.039 7293525.904 604764.624 7293524.587 604763.154 7293523.234 604762.153 7293521.526 604762.053 7293520.653 604762.03 7293518.654 604761.923 7293517.987 604761.171 7293516.142 604760.128 7293514.437 604760.068 7293514.104 604759.7 7293512.14 604759.259 7293510.19 604758.742 7293508.513 604757.879 7293506.714 604756.482 7293505.301 604755.516 7293504.78 604753.564 7293504.545 604752.721 7293505 604750.076 7293507.987 604749.195 7293502.218 604748.118 7293487.895 604748.395 7293475.696 604747.103 7293469.143 604745.835 7293458.865 604746.479 7293452.025 604746.98 7293445.939 604744.556 7293434.079 604744.154 7293431.491 604745.463 7293415.365 604746.254 7293405.127 604746.435 7293402.493 604747.203 7293390.956 604743.037 7293384.339 604728.854 7293379.325 604714.742 7293374.245 604710.684 7293372.311 604706.993 7293370.318 604702.241 7293365.573 604691.032 7293361.509 604684.669 7293360.829 604678.063 7293358.735 604674.74 7293351.475 604675.951 7293340.122 604673.846 7293331.255 604671.34 7293325.263 604665.138 7293318.714 604657.506 7293314.68 604644.518 7293307.381 604636.058 7293302.523 604624.065 7293294.766 604607.857 7293276.826 604587.433 7293261.234 604579.655 7293258.671 604572.897 7293258.348 604558.94 7293257.05 604549.132 7293253.468 604534.831 7293250.773 604509.384 7293252.703 604504.516 7293246.914 604494.833 7293245.028 604486.289 7293244.079 604476.519 7293244.959 604454.437 7293242.748 604443.602 7293240.228 604433.28 7293234.118 604397.722 7293221.404 604389.995 7293218.402 604377.861 7293210.641 604365.526 7293212.327 604358.71 7293208.874 604350.148 7293207.858 604337.031 7293205.345 604325.818 7293206.932 604309.918 7293200.692 604286.851 7293196.336 604270.765 7293188.939 604265.482 7293169.355 604262.275 7293145.593 604255.479 7293129.887 604250.264 7293123.224 604227.361 7293100.012 604216.136 7293092.817 604163.397 7293082.386 604124.193 7293071.952 604117.204 7293071.456 604111.373 7293071.582 604096.73 7293068.779 604089.645 7293067.25 604080.659 7293067.926 604022.822 7293081.986 603960.862 7293122.247 603941.139 7293133.961 603922.542 7293144.511 603905.605 7293146.041 603886.115 7293154.652 603873.137 7293160.104 603864.912 7293164.336 603855.15 7293167.861 603833.284 7293165.567 603824.683 7293162.826 603814.178 7293153.895 603805.629 7293146.28 603799.797 7293141.016 603796.144 7293138.085 603789.238 7293136.122 603782.719 7293140.658 603780.721 7293140.215 603772.476 7293134.2 603761.236 7293134.878 603748.197 7293139.293 603731.273 7293137.38 603723.557 7293131.402 603720.929 7293127.502 603717.238 7293124.58 603715.017 7293123.494</gml:posList></gml:LinearRing></gml:exterior></gml:Polygon></cp:geometry><cp:inspireId><base:Identifier><base:localId>57619618</base:localId><base:namespace>http://paikkatiedot.fi/so/1001077/cp/CadastralParcel/</base:namespace></base:Identifier></cp:inspireId><cp:label>305-415-92-1</cp:label><cp:nationalCadastralReference>30541500920001</cp:nationalCadastralReference><cp:referencePoint><gml:Point srsDimension="2" srsName="http://www.opengis.net/gml/srs/epsg.xml#3067"><gml:pos>604539.173 7292827.712</gml:pos></gml:Point></cp:referencePoint><cp:basicPropertyUnit xlink:href="FI_CP_BASICPROPERTYUNIT_30541500920001"/></cp:CadastralParcel></wfs:member><wfs:member><cp:CadastralParcel gml:id="FI_CP_CADASTRALPARCEL_94806966"><gml:identifier codeSpace="http://paikkatiedot.fi">http://paikkatiedot.fi/so/1001077/cp/CadastralParcel/94806966</gml:identifier><cp:beginLifespanVersion>2013-05-16T00:00:00Z</cp:beginLifespanVersion><cp:geometry><gml:Polygon srsDimension="2" srsName="http://www.opengis.net/gml/srs/epsg.xml#3067"><gml:exterior><gml:LinearRing><gml:posList>604750.076 7293507.987 604749.174 7293508.557 604747.305 7293509.257 604745.382 7293509.805 604743.592 7293510.67 604742.62 7293512.137 604742.079 7293514.058 604741.622 7293516.004 604741.248 7293517.186 604740.077 7293518.728 604738.499 7293518.501 604736.605 7293517.871 604736.243 7293517.831 604734.329 7293518.299 604732.789 7293519.564 604731.61 7293521.172 604731.229 7293521.901 604730.446 7293523.74 604729.599 7293525.55 604729.248 7293526.117 604727.973 7293527.654 604726.434 7293528.924 604722.759 7293531.084 604721.922 7293531.727 604720.342 7293532.952 604718.509 7293533.699 604717.879 7293533.683 604715.945 7293533.19 604714.006 7293532.72 604712.665 7293532.795 604710.787 7293533.465 604710.393 7293533.679 604708.728 7293534.783 604707.101 7293535.943 604705.466 7293536.902 604703.678 7293537.796 604702.742 7293538.247 604699.189 7293540.083 604697.486 7293541.127 604695.92 7293542.472 604694.97 7293544.21 604694.704 7293545.885 604694.511 7293547.875 604693.56 7293549.488 604692.977 7293549.423 604691.03 7293548.987 604690.263 7293549.189 604688.808 7293550.537 604687.48 7293552.028 604686.016 7293552.82 604684.096 7293553.37 604682.218 7293554.044 604680.61 7293555.191 604678.865 7293556.137 604678.142 7293556.196 604676.161 7293555.944 604674.174 7293555.867 604673.631 7293556.058 604672.072 7293557.29 604670.709 7293558.752 604670.307 7293559.13 604668.711 7293560.331 604667.016 7293561.39 604665.478 7293562.305 604663.676 7293563.165 604662.665 7293563.481 604660.7 7293563.841 604659.495 7293563.97 604657.81 7293564.087 604657.501 7293564.109 604657.596 7293564.222 604657.668 7293564.307 604658.176 7293565.345 604658.748 7293567.259 604659.548 7293568.436 604661.264 7293569.404 604663.396 7293569.889 604663.664 7293570.172 604663.707 7293572.051 604663.385 7293572.409 604661.885 7293573.729 604662.898 7293574.327 604662.765 7293575.963 604661.648 7293577.621 604661.136 7293579.443 604661.334 7293581.43 604661.511 7293582.459 604661.811 7293584.435 604661.926 7293586.429 604661.877 7293587.49 604661.666 7293589.478 604661.484 7293591.468 604661.463 7293592.168 604661.447 7293594.166 604661.294 7293596.158 604661.147 7293596.856 604660.612 7293598.782 604660.365 7293599.647 604659.919 7293601.595 604659.728 7293603.581 604660.198 7293605.509 604660.712 7293606.26 604662.055 7293607.74 604663.476 7293609.146 604664.262 7293610.153 604665.257 7293611.885 604666.049 7293613.72 604666.803 7293615.571 604667.735 7293617.502 604668.788 7293619.199 604670.14 7293620.662 604671.898 7293621.59 604673.735 7293621.899 604675.722 7293622.109 604677.589 7293622.776 604678.296 7293623.531 604679.026 7293625.38 604679.242 7293627.364 604679.206 7293628.309 604678.852 7293630.273 604678.128 7293632.135 604677.164 7293633.885 604676.034 7293635.533 604675.502 7293636.223 604674.221 7293637.758 604672.887 7293639.246 604668.85 7293643.682 604667.639 7293645.147 604666.415 7293646.729 604664.013 7293649.925 604661.536 7293653.124 604658.957 7293656.179 604657.58 7293657.628 604656.137 7293659.012 604654.531 7293660.404 604652.96 7293661.64 604649.706 7293663.964 604648.038 7293665.07 604646.338 7293666.123 604644.589 7293667.092 604642.775 7293667.929 604640.774 7293668.667 604638.85 7293669.211 604636.892 7293669.612 604634.915 7293669.906 604632.931 7293670.148 604628.953 7293670.555 604628.464 7293670.787 604626.625 7293671.569 604624.632 7293672.11 604622.649 7293672.353 604620.653 7293672.449 604618.653 7293672.482 604616.753 7293672.552 604612.762 7293672.788 604610.777 7293673.021 604610.405 7293673.075 604608.436 7293673.415 604606.437 7293673.732 604604.478 7293674.124 604602.602 7293674.805 604602.2 7293675.005 604593.167 7293679.282 604591.315 7293680.035 604589.435 7293680.716 604587.528 7293681.315 604586.224 7293681.665 604582.356 7293682.679 604580.487 7293683.384 604578.707 7293684.293 604577.019 7293685.363 604575.421 7293686.564 604574.748 7293687.124 604573.225 7293688.42 604571.65 7293689.648 604569.897 7293689.657 604569.746 7293689.152 604569.532 7293687.164 604568.964 7293685.299 604567.728 7293685.576 604566.09 7293686.721 604564.521 7293687.847 604562.865 7293688.965 604557.868 7293692.281 604557.493 7293692.536 604555.853 7293693.68 604552.342 7293695.759 604550.742 7293696.952 604549.449 7293698.469 604548.749 7293699.813 604547.746 7293701.543 604546.464 7293703.07 604544.68 7293704.251 604542.787 7293704.881 604540.809 7293705.157 604538.811 7293705.181 604530.83 7293704.68 604529.889 7293704.679 604527.892 7293704.764 604525.904 7293704.97 604523.933 7293705.302 604521.984 7293705.744 604520.051 7293706.259 604518.138 7293706.837 604516.242 7293707.47 604514.866 7293707.96 604512.99 7293708.648 604509.213 7293709.959 604507.286 7293710.493 604505.329 7293710.9 604503.348 7293711.165 604501.353 7293711.277 604500.165 7293711.255 604498.169 7293711.148 604496.174 7293711.026 604494.176 7293710.977 604492.185 7293711.14 604490.255 7293711.646 604489.278 7293712.126 604487.645 7293713.276 604486.179 7293714.634 604484.814 7293716.094 604483.469 7293717.573 604482.076 7293719.006 604480.868 7293720.085 604479.286 7293721.307 604478.754 7293721.652 604477.571 7293721.976 604476.017 7293722.213 604474.078 7293722.346 604472.081 7293722.441 604470.946 7293722.539 604468.968 7293722.825 604466.999 7293723.169 604465.551 7293723.43 604463.588 7293723.806 604461.64 7293724.252 604459.736 7293724.86 604458.809 7293725.225 604456.994 7293726.063 604453.473 7293727.958 604452.875 7293728.276 604451.11 7293729.212 604449.364 7293730.186 604447.686 7293731.272 604445.973 7293732.605 604441.418 7293736.505 604440.211 7293737.402 604438.592 7293738.575 604437.042 7293739.837 604435.658 7293741.276 604434.973 7293742.194 604433.782 7293743.799 604433.28 7293744.229 604432.19 7293744.393 604430.211 7293744.675 604428.069 7293745.004 604426.164 7293745.591 604424.722 7293746.465 604423.227 7293747.79 604420.5 7293750.739 604419.151 7293752.02 604417.366 7293751.117 604351.093 7293717.574 604172.699 7293627.282 603994.303 7293536.99 603815.909 7293446.699 603637.514 7293356.407 603713.41 7293128.319 603715.017 7293123.494 603717.238 7293124.58 603720.929 7293127.502 603723.557 7293131.402 603731.273 7293137.38 603748.197 7293139.293 603761.236 7293134.878 603772.476 7293134.2 603780.721 7293140.215 603782.719 7293140.658 603789.238 7293136.122 603796.144 7293138.085 603799.797 7293141.016 603805.629 7293146.28 603814.178 7293153.895 603824.683 7293162.826 603833.284 7293165.567 603855.15 7293167.861 603864.912 7293164.336 603873.137 7293160.104 603886.115 7293154.652 603905.605 7293146.041 603922.542 7293144.511 603941.139 7293133.961 603960.862 7293122.247 604022.822 7293081.986 604080.659 7293067.926 604089.645 7293067.25 604096.73 7293068.779 604111.373 7293071.582 604117.204 7293071.456 604124.193 7293071.952 604163.397 7293082.386 604216.136 7293092.817 604227.361 7293100.012 604250.264 7293123.224 604255.479 7293129.887 604262.275 7293145.593 604265.482 7293169.355 604270.765 7293188.939 604286.851 7293196.336 604309.918 7293200.692 604325.818 7293206.932 604337.031 7293205.345 604350.148 7293207.858 604358.71 7293208.874 604365.526 7293212.327 604377.861 7293210.641 604389.995 7293218.402 604397.722 7293221.404 604433.28 7293234.118 604443.602 7293240.228 604454.437 7293242.748 604476.519 7293244.959 604486.289 7293244.079 604494.833 7293245.028 604504.516 7293246.914 604509.384 7293252.703 604534.831 7293250.773 604549.132 7293253.468 604558.94 7293257.05 604572.897 7293258.348 604579.655 7293258.671 604587.433 7293261.234 604607.857 7293276.826 604624.065 7293294.766 604636.058 7293302.523 604644.518 7293307.381 604657.506 7293314.68 604665.138 7293318.714 604671.34 7293325.263 604673.846 7293331.255 604675.951 7293340.122 604674.74 7293351.475 604678.063 7293358.735 604684.669 7293360.829 604691.032 7293361.509 604702.241 7293365.573 604706.993 7293370.318 604710.684 7293372.311 604714.742 7293374.245 604728.854 7293379.325 604743.037 7293384.339 604747.203 7293390.956 604746.435 7293402.493 604746.254 7293405.127 604745.463 7293415.365 604744.154 7293431.491 604744.556 7293434.079 604746.98 7293445.939 604746.479 7293452.025 604745.835 7293458.865 604747.103 7293469.143 604748.395 7293475.696 604748.118 7293487.895 604749.195 7293502.218 604750.076 7293507.987</gml:posList></gml:LinearRing></gml:exterior></gml:Polygon></cp:geometry><cp:inspireId><base:Identifier><base:localId>94806966</base:localId><base:namespace>http://paikkatiedot.fi/so/1001077/cp/CadastralParcel/</base:namespace></base:Identifier></cp:inspireId><cp:label>305-415-90-4</cp:label><cp:nationalCadastralReference>30541500900004</cp:nationalCadastralReference><cp:referencePoint><gml:Point srsDimension="2" srsName="http://www.opengis.net/gml/srs/epsg.xml#3067"><gml:pos>604229.38 7293524.587</gml:pos></gml:Point></cp:referencePoint><cp:basicPropertyUnit xlink:href="FI_CP_BASICPROPERTYUNIT_30541500900004"/></cp:CadastralParcel></wfs:member></wfs:FeatureCollection>