<?xml version="1.0" encoding="UTF-8"?><wfs:FeatureCollection xmlns:wfs="http://www.opengis.net/wfs/2.0" xmlns:xs="http://www.w3.org/2001/XMLSchema" xmlns:au="http://inspire.ec.europa.eu/schemas/au/4.0" xmlns:gml="http://www.opengis.net/gml/3.2" xmlns:gn="http://inspire.ec.europa.eu/schemas/gn/4.0" xmlns:cp="http://inspire.ec.europa.eu/schemas/cp/4.0" xmlns:xsi="http://www.w3.org/2001/XMLSchema-instance" xmlns:xlink="http://www.w3.org/1999/xlink" xmlns:base="http://inspire.ec.europa.eu/schemas/base/3.3" numberMatched="unknown" numberReturned="7" timeStamp="2021-11-15T13:05:30.135Z" xsi:schemaLocation="http://www.opengis.net/wfs/2.0 http://schemas.opengis.net/wfs/2.0/wfs.xsd http://inspire.ec.europa.eu/schemas/cp/4.0 http://inspire.ec.europa.eu/schemas/cp/4.0/CadastralParcels.xsd http://www.opengis.net/gml/3.2 http://schemas.opengis.net/gml/3.2.1/gml.xsd"><wfs:member><cp:CadastralParcel gml:id="FI_CP_CADASTRALPARCEL_269441260"><gml:identifier codeSpace="http://paikkatiedot.fi">http://paikkatiedot.fi/so/1001077/cp/CadastralParcel/269441260</gml:identifier><cp:beginLifespanVersion>2021-06-22T00:00:00Z</cp:beginLifespanVersion><cp:geometry><gml:Polygon srsDimension="2" srsName="http://www.opengis.net/gml/srs/epsg.xml#3067"><gml:exterior><gml:LinearRing><gml:posList>443710.221 6775298.901 443670.946 6775250.276 443655.304 6775228.293 443608.989 6775251.842 443627.213 6775211.909 443633.632 6775178.793 443625.771 6775156.907 443618.952 6775139.41 443619.984 6775123.448 443689.472 6775078.882 443717.649 6775060.696 443767.089 6775038.851 443795.968 6775026.889 443828.153 6775012.712 443878.345 6774992.013 443930.426 6774980.896 443996.694 6775095.277 444030.569 6775155.365 444121.811 6775312.651 443911.886 6775588.771 443975.768 6775690.297 444290.341 6775630.125 444317.429 6775843.44 444326.124 6776035.263 444218.968 6775873.626 444043.672 6775926.302 443798.775 6775545.308 443778.753 6775514.159 443778.914 6775514.059 443796.65 6775502.984 443843.823 6775483.178 443813.682 6775429.672 443778.701 6775379.937 443772.834 6775371.302 443736.495 6775331.43 443710.221 6775298.901</gml:posList></gml:LinearRing></gml:exterior></gml:Polygon></cp:geometry><cp:inspireId><base:Identifier><base:localId>269441260</base:localId><base:namespace>http://paikkatiedot.fi/so/1001077/cp/CadastralParcel/</base:namespace></base:Identifier></cp:inspireId><cp:label>111-404-3-172</cp:label><cp:nationalCadastralReference>11140400030172</cp:nationalCadastralReference><cp:referencePoint><gml:Point srsDimension="2" srsName="http://www.opengis.net/gml/srs/epsg.xml#3067"><gml:pos>443968.87 6775242.558</gml:pos></gml:Point></cp:referencePoint><cp:basicPropertyUnit xlink:href="FI_CP_BASICPROPERTYUNIT_11140400030172"/></cp:CadastralParcel></wfs:member><wfs:member><cp:CadastralParcel gml:id="FI_CP_CADASTRALPARCEL_269443052"><gml:identifier codeSpace="http://paikkatiedot.fi">http://paikkatiedot.fi/so/1001077/cp/CadastralParcel/269443052</gml:identifier><cp:beginLifespanVersion>2014-10-16T00:00:00Z</cp:beginLifespanVersion><cp:geometry><gml:Polygon srsDimension="2" srsName="http://www.opengis.net/gml/srs/epsg.xml#3067"><gml:exterior><gml:LinearRing><gml:posList>445026.973 6774781.161 445202.461 6775020.162 445330.815 6775196.167 445497.95 6775423.856 445227.997 6775599.68 445256.026 6775645.188 445001.503 6775785.128 444945.874 6775690.31 445026.033 6775658.478 445120.601 6775439.238 445038.543 6775313.456 444983.961 6775229.792 444852.416 6775029.715 444849.56 6775025.39 444824.561 6775023.795 444741.717 6775018.511 444676.76 6775244.344 444427.001 6774825.141 444445.15 6774822.172 444454.313 6774817.332 444475.732 6774802.51 444514.372 6774784.587 444547.224 6774772.901 444570.215 6774768.369 444589.616 6774764.848 444622.612 6774763.297 444652.72 6774743.622 444674.606 6774736.988 444696.27 6774735.188 444714.746 6774718.463 444868.124 6774617.009 444889.824 6774593.434 445026.973 6774781.161</gml:posList></gml:LinearRing></gml:exterior></gml:Polygon></cp:geometry><cp:inspireId><base:Identifier><base:localId>269443052</base:localId><base:namespace>http://paikkatiedot.fi/so/1001077/cp/CadastralParcel/</base:namespace></base:Identifier></cp:inspireId><cp:label>111-404-3-1</cp:label><cp:nationalCadastralReference>11140400030001</cp:nationalCadastralReference><cp:referencePoint><gml:Point srsDimension="2" srsName="http://www.opengis.net/gml/srs/epsg.xml#3067"><gml:pos>444906.711 6774928.569</gml:pos></gml:Point></cp:referencePoint><cp:basicPropertyUnit xlink:href="FI_CP_BASICPROPERTYUNIT_11140400030001"/></cp:CadastralParcel></wfs:member><wfs:member><cp:CadastralParcel gml:id="FI_CP_CADASTRALPARCEL_269443055"><gml:identifier codeSpace="http://paikkatiedot.fi">http://paikkatiedot.fi/so/1001077/cp/CadastralParcel/269443055</gml:identifier><cp:beginLifespanVersion>2021-06-22T00:00:00Z</cp:beginLifespanVersion><cp:geometry><gml:Polygon srsDimension="2" srsName="http://www.opengis.net/gml/srs/epsg.xml#3067"><gml:exterior><gml:LinearRing><gml:posList>444239.846 6774910.256 444278.674 6774897.549 444355.349 6774862.479 444371.256 6774857.466 444395.438 6774845.982 444405.354 6774837.468 444427.001 6774825.141 444676.76 6775244.344 444233.678 6775183.24 444214.482 6775075.293 444107.744 6775093.869 444108.094 6775095.837 444120.856 6775167.682 444030.569 6775155.365 443996.694 6775095.277 443930.426 6774980.896 443970.502 6774971.088 443987.969 6774970.087 444022.168 6774973.679 444035.318 6774972.894 444049.35 6774968.144 444082.023 6774953.512 444135.004 6774939.475 444181.338 6774925.624 444239.846 6774910.256</gml:posList></gml:LinearRing></gml:exterior></gml:Polygon></cp:geometry><cp:inspireId><base:Identifier><base:localId>269443055</base:localId><base:namespace>http://paikkatiedot.fi/so/1001077/cp/CadastralParcel/</base:namespace></base:Identifier></cp:inspireId><cp:label>111-404-3-130</cp:label><cp:nationalCadastralReference>11140400030130</cp:nationalCadastralReference><cp:referencePoint><gml:Point srsDimension="2" srsName="http://www.opengis.net/gml/srs/epsg.xml#3067"><gml:pos>444252.161 6775147.088</gml:pos></gml:Point></cp:referencePoint><cp:basicPropertyUnit xlink:href="FI_CP_BASICPROPERTYUNIT_11140400030130"/></cp:CadastralParcel></wfs:member><wfs:member><cp:CadastralParcel gml:id="FI_CP_CADASTRALPARCEL_29212079"><gml:identifier codeSpace="http://paikkatiedot.fi">http://paikkatiedot.fi/so/1001077/cp/CadastralParcel/29212079</gml:identifier><cp:beginLifespanVersion>2021-06-22T00:00:00Z</cp:beginLifespanVersion><cp:geometry><gml:Polygon srsDimension="2" srsName="http://www.opengis.net/gml/srs/epsg.xml#3067"><gml:exterior><gml:LinearRing><gml:posList>444565.226 6776079.148 444546.188 6776145.963 444499.606 6776299.739 444433.979 6776199.198 444326.124 6776035.263 444317.429 6775843.44 444290.341 6775630.125 443975.768 6775690.297 443911.886 6775588.771 444121.811 6775312.651 444565.226 6776079.148</gml:posList></gml:LinearRing></gml:exterior></gml:Polygon></cp:geometry><cp:inspireId><base:Identifier><base:localId>29212079</base:localId><base:namespace>http://paikkatiedot.fi/so/1001077/cp/CadastralParcel/</base:namespace></base:Identifier></cp:inspireId><cp:label>111-404-3-76</cp:label><cp:nationalCadastralReference>11140400030076</cp:nationalCadastralReference><cp:referencePoint><gml:Point srsDimension="2" srsName="http://www.opengis.net/gml/srs/epsg.xml#3067"><gml:pos>444096.245 6775373.214</gml:pos></gml:Point></cp:referencePoint><cp:basicPropertyUnit xlink:href="FI_CP_BASICPROPERTYUNIT_11140400030076"/></cp:CadastralParcel></wfs:member><wfs:member><cp:CadastralParcel gml:id="FI_CP_CADASTRALPARCEL_29212282"><gml:identifier codeSpace="http://paikkatiedot.fi">http://paikkatiedot.fi/so/1001077/cp/CadastralParcel/29212282</gml:identifier><cp:beginLifespanVersion>2010-01-22T01:00:00Z</cp:beginLifespanVersion><cp:geometry><gml:Polygon srsDimension="2" srsName="http://www.opengis.net/gml/srs/epsg.xml#3067"><gml:exterior><gml:LinearRing><gml:posList>444676.76 6775244.344 444741.717 6775018.511 444824.561 6775023.795 444849.56 6775025.39 444852.416 6775029.715 444983.961 6775229.792 445038.543 6775313.456 445120.601 6775439.238 445026.033 6775658.478 444945.874 6775690.31 444852.413 6775535.153 444676.76 6775244.344</gml:posList></gml:LinearRing></gml:exterior></gml:Polygon></cp:geometry><cp:inspireId><base:Identifier><base:localId>29212282</base:localId><base:namespace>http://paikkatiedot.fi/so/1001077/cp/CadastralParcel/</base:namespace></base:Identifier></cp:inspireId><cp:label>111-404-3-72</cp:label><cp:nationalCadastralReference>11140400030072</cp:nationalCadastralReference><cp:referencePoint><gml:Point srsDimension="2" srsName="http://www.opengis.net/gml/srs/epsg.xml#3067"><gml:pos>444915.129 6775406.824</gml:pos></gml:Point></cp:referencePoint><cp:basicPropertyUnit xlink:href="FI_CP_BASICPROPERTYUNIT_11140400030072"/></cp:CadastralParcel></wfs:member><wfs:member><cp:CadastralParcel gml:id="FI_CP_CADASTRALPARCEL_29212284"><gml:identifier codeSpace="http://paikkatiedot.fi">http://paikkatiedot.fi/so/1001077/cp/CadastralParcel/29212284</gml:identifier><cp:beginLifespanVersion>2021-06-22T00:00:00Z</cp:beginLifespanVersion><cp:geometry><gml:Polygon srsDimension="2" srsName="http://www.opengis.net/gml/srs/epsg.xml#3067"><gml:exterior><gml:LinearRing><gml:posList>444121.811 6775312.651 444398.958 6775278.538 444676.76 6775244.344 444852.413 6775535.153 444945.874 6775690.31 444852.412 6775727.973 444852.112 6775728.094 444849.712 6775820.657 444565.226 6776079.148 444121.811 6775312.651</gml:posList></gml:LinearRing></gml:exterior></gml:Polygon></cp:geometry><cp:inspireId><base:Identifier><base:localId>29212284</base:localId><base:namespace>http://paikkatiedot.fi/so/1001077/cp/CadastralParcel/</base:namespace></base:Identifier></cp:inspireId><cp:label>111-404-3-74</cp:label><cp:nationalCadastralReference>11140400030074</cp:nationalCadastralReference><cp:referencePoint><gml:Point srsDimension="2" srsName="http://www.opengis.net/gml/srs/epsg.xml#3067"><gml:pos>444437.411 6775335.788</gml:pos></gml:Point></cp:referencePoint><cp:basicPropertyUnit xlink:href="FI_CP_BASICPROPERTYUNIT_11140400030074"/></cp:CadastralParcel></wfs:member><wfs:member><cp:CadastralParcel gml:id="FI_CP_CADASTRALPARCEL_396995257"><gml:identifier codeSpace="http://paikkatiedot.fi">http://paikkatiedot.fi/so/1001077/cp/CadastralParcel/396995257</gml:identifier><cp:beginLifespanVersion>2021-06-22T00:00:00Z</cp:beginLifespanVersion><cp:geometry><gml:Polygon srsDimension="2" srsName="http://www.opengis.net/gml/srs/epsg.xml#3067"><gml:exterior><gml:LinearRing><gml:posList>444676.76 6775244.344 444398.958 6775278.538 444121.811 6775312.651 444030.569 6775155.365 444120.856 6775167.682 444233.678 6775183.24 444676.76 6775244.344</gml:posList></gml:LinearRing></gml:exterior></gml:Polygon></cp:geometry><cp:inspireId><base:Identifier><base:localId>396995257</base:localId><base:namespace>http://paikkatiedot.fi/so/1001077/cp/CadastralParcel/</base:namespace></base:Identifier></cp:inspireId><cp:label>111-404-3-14</cp:label><cp:nationalCadastralReference>11140400030014</cp:nationalCadastralReference><cp:referencePoint><gml:Point srsDimension="2" srsName="http://www.opengis.net/gml/srs/epsg.xml#3067"><gml:pos>444290.564 6775231.672</gml:pos></gml:Point></cp:referencePoint><cp:basicPropertyUnit xlink:href="FI_CP_BASICPROPERTYUNIT_11140400030014"/></cp:CadastralParcel></wfs:member></wfs:FeatureCollection>