<?xml version="1.0" encoding="UTF-8"?><wfs:FeatureCollection xmlns:wfs="http://www.opengis.net/wfs/2.0" xmlns:xs="http://www.w3.org/2001/XMLSchema" xmlns:au="http://inspire.ec.europa.eu/schemas/au/4.0" xmlns:gml="http://www.opengis.net/gml/3.2" xmlns:gn="http://inspire.ec.europa.eu/schemas/gn/4.0" xmlns:cp="http://inspire.ec.europa.eu/schemas/cp/4.0" xmlns:xsi="http://www.w3.org/2001/XMLSchema-instance" xmlns:xlink="http://www.w3.org/1999/xlink" xmlns:base="http://inspire.ec.europa.eu/schemas/base/3.3" numberMatched="unknown" numberReturned="8" timeStamp="2021-11-15T13:09:15.438Z" xsi:schemaLocation="http://www.opengis.net/wfs/2.0 http://schemas.opengis.net/wfs/2.0/wfs.xsd http://inspire.ec.europa.eu/schemas/cp/4.0 http://inspire.ec.europa.eu/schemas/cp/4.0/CadastralParcels.xsd http://www.opengis.net/gml/3.2 http://schemas.opengis.net/gml/3.2.1/gml.xsd"><wfs:member><cp:CadastralParcel gml:id="FI_CP_CADASTRALPARCEL_126185885"><gml:identifier codeSpace="http://paikkatiedot.fi">http://paikkatiedot.fi/so/1001077/cp/CadastralParcel/126185885</gml:identifier><cp:beginLifespanVersion>2003-10-03T00:00:00Z</cp:beginLifespanVersion><cp:geometry><gml:Polygon srsDimension="2" srsName="http://www.opengis.net/gml/srs/epsg.xml#3067"><gml:exterior><gml:LinearRing><gml:posList>439675.981 7073859.893 440016.587 7073913.103 440017.673 7073913.273 440016.632 7073919.966 440001.611 7074016.488 439999.77 7074018.178 439862.808 7074143.913 439940.665 7074207.082 439571.908 7074526.255 439569.489 7074528.348 439675.981 7073859.893</gml:posList></gml:LinearRing></gml:exterior></gml:Polygon></cp:geometry><cp:inspireId><base:Identifier><base:localId>126185885</base:localId><base:namespace>http://paikkatiedot.fi/so/1001077/cp/CadastralParcel/</base:namespace></base:Identifier></cp:inspireId><cp:label>626-403-4-37</cp:label><cp:nationalCadastralReference>62640300040037</cp:nationalCadastralReference><cp:referencePoint><gml:Point srsDimension="2" srsName="http://www.opengis.net/gml/srs/epsg.xml#3067"><gml:pos>439681.472 7074216.317</gml:pos></gml:Point></cp:referencePoint><cp:basicPropertyUnit xlink:href="FI_CP_BASICPROPERTYUNIT_62640300040037"/></cp:CadastralParcel></wfs:member><wfs:member><cp:CadastralParcel gml:id="FI_CP_CADASTRALPARCEL_396934303"><gml:identifier codeSpace="http://paikkatiedot.fi">http://paikkatiedot.fi/so/1001077/cp/CadastralParcel/396934303</gml:identifier><cp:beginLifespanVersion>2021-06-30T00:00:00Z</cp:beginLifespanVersion><cp:geometry><gml:Polygon srsDimension="2" srsName="http://www.opengis.net/gml/srs/epsg.xml#3067"><gml:exterior><gml:LinearRing><gml:posList>440189.655 7074625.231 440209.9 7074491.851 440210.274 7074489.38 440229.574 7074472.086 440255.327 7074502.421 440811.929 7074014.095 440814.92 7074017.455 440892.531 7074104.651 441002.97 7074008.893 441005.464 7074009.06 441164.425 7074019.714 441049.789 7074758.691 440189.655 7074625.231</gml:posList></gml:LinearRing></gml:exterior></gml:Polygon></cp:geometry><cp:inspireId><base:Identifier><base:localId>396934303</base:localId><base:namespace>http://paikkatiedot.fi/so/1001077/cp/CadastralParcel/</base:namespace></base:Identifier></cp:inspireId><cp:label>626-403-91-29</cp:label><cp:nationalCadastralReference>62640300910029</cp:nationalCadastralReference><cp:referencePoint><gml:Point srsDimension="2" srsName="http://www.opengis.net/gml/srs/epsg.xml#3067"><gml:pos>440570.246 7074511.831</gml:pos></gml:Point></cp:referencePoint><cp:basicPropertyUnit xlink:href="FI_CP_BASICPROPERTYUNIT_62640300910029"/></cp:CadastralParcel></wfs:member><wfs:member><cp:CadastralParcel gml:id="FI_CP_CADASTRALPARCEL_55500313"><gml:identifier codeSpace="http://paikkatiedot.fi">http://paikkatiedot.fi/so/1001077/cp/CadastralParcel/55500313</gml:identifier><cp:beginLifespanVersion>2021-06-30T00:00:00Z</cp:beginLifespanVersion><cp:geometry><gml:Polygon srsDimension="2" srsName="http://www.opengis.net/gml/srs/epsg.xml#3067"><gml:exterior><gml:LinearRing><gml:posList>439487.135 7076391.227 439482.776 7076388.551 439320.896 7076289.275 439150.468 7076184.656 438980.051 7076080.175 438792.646 7075965.113 438720.537 7075920.945 438741.091 7075871.056 439439.566 7075980.785 439637.073 7076011.814 439686.45 7076019.571 439692.785 7075980.038 439724.472 7075782.669 439755.598 7075588.58 439784.657 7075407.317 439827.38 7075140.964 439867.085 7074880.977 439867.564 7074877.901 439980.905 7074146.526 440256.044 7074187.384 440210.274 7074489.38 440209.9 7074491.851 440189.655 7074625.231 440115.983 7075083.884 440058.48 7075452.02 440010.115 7075761.19 439959.054 7076088.093 439908.425 7076412.033 439874.73 7076629.062 439832.141 7076602.925 439661.679 7076498.373 439487.135 7076391.227</gml:posList></gml:LinearRing></gml:exterior></gml:Polygon></cp:geometry><cp:inspireId><base:Identifier><base:localId>55500313</base:localId><base:namespace>http://paikkatiedot.fi/so/1001077/cp/CadastralParcel/</base:namespace></base:Identifier></cp:inspireId><cp:label>626-403-4-47</cp:label><cp:nationalCadastralReference>62640300040047</cp:nationalCadastralReference><cp:referencePoint><gml:Point srsDimension="2" srsName="http://www.opengis.net/gml/srs/epsg.xml#3067"><gml:pos>439602.562 7076243.378</gml:pos></gml:Point></cp:referencePoint><cp:basicPropertyUnit xlink:href="FI_CP_BASICPROPERTYUNIT_62640300040047"/></cp:CadastralParcel></wfs:member><wfs:member><cp:CadastralParcel gml:id="FI_CP_CADASTRALPARCEL_55500462"><gml:identifier codeSpace="http://paikkatiedot.fi">http://paikkatiedot.fi/so/1001077/cp/CadastralParcel/55500462</gml:identifier><cp:beginLifespanVersion>2018-10-18T00:00:00Z</cp:beginLifespanVersion><cp:geometry><gml:Polygon srsDimension="2" srsName="http://www.opengis.net/gml/srs/epsg.xml#3067"><gml:exterior><gml:LinearRing><gml:posList>439940.665 7074207.082 439862.808 7074143.913 439999.77 7074018.178 440001.611 7074016.488 439980.905 7074146.526 439867.564 7074877.901 439866.072 7074876.152 439569.489 7074528.348 439571.908 7074526.255 439940.665 7074207.082</gml:posList></gml:LinearRing></gml:exterior></gml:Polygon></cp:geometry><cp:inspireId><base:Identifier><base:localId>55500462</base:localId><base:namespace>http://paikkatiedot.fi/so/1001077/cp/CadastralParcel/</base:namespace></base:Identifier></cp:inspireId><cp:label>626-403-4-36</cp:label><cp:nationalCadastralReference>62640300040036</cp:nationalCadastralReference><cp:referencePoint><gml:Point srsDimension="2" srsName="http://www.opengis.net/gml/srs/epsg.xml#3067"><gml:pos>439674.199 7074485.001</gml:pos></gml:Point></cp:referencePoint><cp:basicPropertyUnit xlink:href="FI_CP_BASICPROPERTYUNIT_62640300040036"/></cp:CadastralParcel></wfs:member><wfs:member><cp:CadastralParcel gml:id="FI_CP_CADASTRALPARCEL_55688052"><gml:identifier codeSpace="http://paikkatiedot.fi">http://paikkatiedot.fi/so/1001077/cp/CadastralParcel/55688052</gml:identifier><cp:beginLifespanVersion>2021-06-30T00:00:00Z</cp:beginLifespanVersion><cp:geometry><gml:Polygon srsDimension="2" srsName="http://www.opengis.net/gml/srs/epsg.xml#3067"><gml:exterior><gml:LinearRing><gml:posList>440115.983 7075083.884 440189.655 7074625.231 441049.789 7074758.691 441130.635 7074772.057 441436.171 7074485.757 441462.569 7074310.231 441462.944 7074307.76 441166.439 7074021.658 441164.425 7074019.714 441179.042 7073929.351 441543.422 7073986.72 442124.296 7074078.174 442175.395 7073827.523 442209.843 7073825.912 442712.802 7073800.532 442713.997 7073800.472 442986.615 7073786.715 442990.11 7073786.539 442786.364 7074233.053 442782.899 7074232.564 442111.763 7074137.94 442034.198 7074509.29 441988.597 7074649.739 442125.305 7074714.831 441668.636 7075759.917 441612.592 7075888.155 441524.408 7076089.931 441515.242 7076085.943 440792.54 7075771.485 440654.263 7075711.305 440479.017 7075635.052 440287.628 7075551.769 440104.269 7075471.979 440058.48 7075452.02 440115.983 7075083.884</gml:posList></gml:LinearRing></gml:exterior></gml:Polygon></cp:geometry><cp:inspireId><base:Identifier><base:localId>55688052</base:localId><base:namespace>http://paikkatiedot.fi/so/1001077/cp/CadastralParcel/</base:namespace></base:Identifier></cp:inspireId><cp:label>626-403-86-27</cp:label><cp:nationalCadastralReference>62640300860027</cp:nationalCadastralReference><cp:referencePoint><gml:Point srsDimension="2" srsName="http://www.opengis.net/gml/srs/epsg.xml#3067"><gml:pos>440851.807 7075206.206</gml:pos></gml:Point></cp:referencePoint><cp:basicPropertyUnit xlink:href="FI_CP_BASICPROPERTYUNIT_62640300860027"/></cp:CadastralParcel></wfs:member><wfs:member><cp:CadastralParcel gml:id="FI_CP_CADASTRALPARCEL_55688064"><gml:identifier codeSpace="http://paikkatiedot.fi">http://paikkatiedot.fi/so/1001077/cp/CadastralParcel/55688064</gml:identifier><cp:beginLifespanVersion>2021-06-30T00:00:00Z</cp:beginLifespanVersion><cp:geometry><gml:Polygon srsDimension="2" srsName="http://www.opengis.net/gml/srs/epsg.xml#3067"><gml:exterior><gml:LinearRing><gml:posList>440255.327 7074502.421 440229.574 7074472.086 440210.274 7074489.38 440256.044 7074187.384 440328.224 7073726.396 440371.718 7073438.678 440561.726 7073469.064 440640.69 7073481.693 440939.576 7073529.492 441235.633 7073573.966 441179.042 7073929.351 441164.425 7074019.714 441005.464 7074009.06 441002.97 7074008.893 440892.531 7074104.651 440814.92 7074017.455 440811.929 7074014.095 440255.327 7074502.421</gml:posList></gml:LinearRing></gml:exterior></gml:Polygon></cp:geometry><cp:inspireId><base:Identifier><base:localId>55688064</base:localId><base:namespace>http://paikkatiedot.fi/so/1001077/cp/CadastralParcel/</base:namespace></base:Identifier></cp:inspireId><cp:label>626-403-91-10</cp:label><cp:nationalCadastralReference>62640300910010</cp:nationalCadastralReference><cp:referencePoint><gml:Point srsDimension="2" srsName="http://www.opengis.net/gml/srs/epsg.xml#3067"><gml:pos>440570.383 7074067.327</gml:pos></gml:Point></cp:referencePoint><cp:basicPropertyUnit xlink:href="FI_CP_BASICPROPERTYUNIT_62640300910010"/></cp:CadastralParcel></wfs:member><wfs:member><cp:CadastralParcel gml:id="FI_CP_CADASTRALPARCEL_55688101"><gml:identifier codeSpace="http://paikkatiedot.fi">http://paikkatiedot.fi/so/1001077/cp/CadastralParcel/55688101</gml:identifier><cp:beginLifespanVersion>2018-10-18T00:00:00Z</cp:beginLifespanVersion><cp:geometry><gml:Polygon srsDimension="2" srsName="http://www.opengis.net/gml/srs/epsg.xml#3067"><gml:exterior><gml:LinearRing><gml:posList>440328.224 7073726.396 440256.044 7074187.384 439980.905 7074146.526 440001.611 7074016.488 440328.224 7073726.396</gml:posList></gml:LinearRing></gml:exterior></gml:Polygon></cp:geometry><cp:inspireId><base:Identifier><base:localId>55688101</base:localId><base:namespace>http://paikkatiedot.fi/so/1001077/cp/CadastralParcel/</base:namespace></base:Identifier></cp:inspireId><cp:label>626-403-247-0</cp:label><cp:nationalCadastralReference>62640302470000</cp:nationalCadastralReference><cp:referencePoint><gml:Point srsDimension="2" srsName="http://www.opengis.net/gml/srs/epsg.xml#3067"><gml:pos>440121.748 7073937.703</gml:pos></gml:Point></cp:referencePoint><cp:basicPropertyUnit xlink:href="FI_CP_BASICPROPERTYUNIT_62640302470000"/></cp:CadastralParcel></wfs:member><wfs:member><cp:CadastralParcel gml:id="FI_CP_CADASTRALPARCEL_55688121"><gml:identifier codeSpace="http://paikkatiedot.fi">http://paikkatiedot.fi/so/1001077/cp/CadastralParcel/55688121</gml:identifier><cp:beginLifespanVersion>2018-10-18T00:00:00Z</cp:beginLifespanVersion><cp:geometry><gml:Polygon srsDimension="2" srsName="http://www.opengis.net/gml/srs/epsg.xml#3067"><gml:exterior><gml:LinearRing><gml:posList>439569.489 7074528.348 439866.072 7074876.152 439867.564 7074877.901 439867.085 7074880.977 439827.38 7075140.964 439481.476 7075086.263 439569.489 7074528.348</gml:posList></gml:LinearRing></gml:exterior></gml:Polygon></cp:geometry><cp:inspireId><base:Identifier><base:localId>55688121</base:localId><base:namespace>http://paikkatiedot.fi/so/1001077/cp/CadastralParcel/</base:namespace></base:Identifier></cp:inspireId><cp:label>626-403-4-37</cp:label><cp:nationalCadastralReference>62640300040037</cp:nationalCadastralReference><cp:referencePoint><gml:Point srsDimension="2" srsName="http://www.opengis.net/gml/srs/epsg.xml#3067"><gml:pos>439590.353 7074851.521</gml:pos></gml:Point></cp:referencePoint><cp:basicPropertyUnit xlink:href="FI_CP_BASICPROPERTYUNIT_62640300040037"/></cp:CadastralParcel></wfs:member></wfs:FeatureCollection>