<?xml version="1.0" encoding="UTF-8"?><wfs:FeatureCollection xmlns:wfs="http://www.opengis.net/wfs/2.0" xmlns:xs="http://www.w3.org/2001/XMLSchema" xmlns:au="http://inspire.ec.europa.eu/schemas/au/4.0" xmlns:gml="http://www.opengis.net/gml/3.2" xmlns:gn="http://inspire.ec.europa.eu/schemas/gn/4.0" xmlns:cp="http://inspire.ec.europa.eu/schemas/cp/4.0" xmlns:xsi="http://www.w3.org/2001/XMLSchema-instance" xmlns:xlink="http://www.w3.org/1999/xlink" xmlns:base="http://inspire.ec.europa.eu/schemas/base/3.3" numberMatched="unknown" numberReturned="12" timeStamp="2021-11-15T16:06:05.881Z" xsi:schemaLocation="http://www.opengis.net/wfs/2.0 http://schemas.opengis.net/wfs/2.0/wfs.xsd http://inspire.ec.europa.eu/schemas/cp/4.0 http://inspire.ec.europa.eu/schemas/cp/4.0/CadastralParcels.xsd http://www.opengis.net/gml/3.2 http://schemas.opengis.net/gml/3.2.1/gml.xsd"><wfs:member><cp:CadastralParcel gml:id="FI_CP_CADASTRALPARCEL_203021134"><gml:identifier codeSpace="http://paikkatiedot.fi">http://paikkatiedot.fi/so/1001077/cp/CadastralParcel/203021134</gml:identifier><cp:beginLifespanVersion>2013-01-26T01:00:00Z</cp:beginLifespanVersion><cp:geometry><gml:Polygon srsDimension="2" srsName="http://www.opengis.net/gml/srs/epsg.xml#3067"><gml:exterior><gml:LinearRing><gml:posList>348715.439 6996161.386 348794.745 6996019.513 348803.891 6996003.152 349536.465 6996410.137 349673.573 6996486.307 349652.878 6996545.521 349613.237 6996658.941 349467.619 6996578.121 348715.439 6996161.386</gml:posList></gml:LinearRing></gml:exterior></gml:Polygon></cp:geometry><cp:inspireId><base:Identifier><base:localId>203021134</base:localId><base:namespace>http://paikkatiedot.fi/so/1001077/cp/CadastralParcel/</base:namespace></base:Identifier></cp:inspireId><cp:label>5-401-23-101</cp:label><cp:nationalCadastralReference>00540100230101</cp:nationalCadastralReference><cp:referencePoint><gml:Point srsDimension="2" srsName="http://www.opengis.net/gml/srs/epsg.xml#3067"><gml:pos>349123.014 6996335.187</gml:pos></gml:Point></cp:referencePoint><cp:basicPropertyUnit xlink:href="FI_CP_BASICPROPERTYUNIT_00540100230101"/></cp:CadastralParcel></wfs:member><wfs:member><cp:CadastralParcel gml:id="FI_CP_CADASTRALPARCEL_358152286"><gml:identifier codeSpace="http://paikkatiedot.fi">http://paikkatiedot.fi/so/1001077/cp/CadastralParcel/358152286</gml:identifier><cp:beginLifespanVersion>2017-10-19T00:00:00Z</cp:beginLifespanVersion><cp:geometry><gml:Polygon srsDimension="2" srsName="http://www.opengis.net/gml/srs/epsg.xml#3067"><gml:exterior><gml:LinearRing><gml:posList>348669.049 6994482.565 348682.712 6994490.093 348690.969 6994592.484 348693.208 6994630.511 348702.016 6994651.952 348707.397 6994661.182 348730.084 6994688.05 348780.292 6994746.321 348384.626 6995470.866 348381.724 6995476.14 348162.769 6995404.586 348167.63 6995395.735 348669.049 6994482.565</gml:posList></gml:LinearRing></gml:exterior></gml:Polygon></cp:geometry><cp:inspireId><base:Identifier><base:localId>358152286</base:localId><base:namespace>http://paikkatiedot.fi/so/1001077/cp/CadastralParcel/</base:namespace></base:Identifier></cp:inspireId><cp:label>5-401-12-196</cp:label><cp:nationalCadastralReference>00540100120196</cp:nationalCadastralReference><cp:referencePoint><gml:Point srsDimension="2" srsName="http://www.opengis.net/gml/srs/epsg.xml#3067"><gml:pos>348417.654 6995021.116</gml:pos></gml:Point></cp:referencePoint><cp:basicPropertyUnit xlink:href="FI_CP_BASICPROPERTYUNIT_00540100120196"/></cp:CadastralParcel></wfs:member><wfs:member><cp:CadastralParcel gml:id="FI_CP_CADASTRALPARCEL_52161712"><gml:identifier codeSpace="http://paikkatiedot.fi">http://paikkatiedot.fi/so/1001077/cp/CadastralParcel/52161712</gml:identifier><cp:beginLifespanVersion>2012-09-08T00:00:00Z</cp:beginLifespanVersion><cp:geometry><gml:Polygon srsDimension="2" srsName="http://www.opengis.net/gml/srs/epsg.xml#3067"><gml:exterior><gml:LinearRing><gml:posList>347210.821 6996788.396 346760.25 6996888.447 346084.775 6997038.405 346098.982 6996993.609 346129.488 6996897.417 346130.72 6996893.533 346159.961 6996801.329 346410.126 6996780.991 346612.814 6996764.513 347950.152 6995937.315 348094.011 6995851.364 348044.319 6995970.933 347797.777 6996564.166 347761.701 6996650.585 347559.67 6997136.253 347288.501 6997189.714 347210.821 6996788.396</gml:posList></gml:LinearRing></gml:exterior></gml:Polygon></cp:geometry><cp:inspireId><base:Identifier><base:localId>52161712</base:localId><base:namespace>http://paikkatiedot.fi/so/1001077/cp/CadastralParcel/</base:namespace></base:Identifier></cp:inspireId><cp:label>5-401-26-14</cp:label><cp:nationalCadastralReference>00540100260014</cp:nationalCadastralReference><cp:referencePoint><gml:Point srsDimension="2" srsName="http://www.opengis.net/gml/srs/epsg.xml#3067"><gml:pos>347354.313 6996684.1</gml:pos></gml:Point></cp:referencePoint><cp:basicPropertyUnit xlink:href="FI_CP_BASICPROPERTYUNIT_00540100260014"/></cp:CadastralParcel></wfs:member><wfs:member><cp:CadastralParcel gml:id="FI_CP_CADASTRALPARCEL_55804993"><gml:identifier codeSpace="http://paikkatiedot.fi">http://paikkatiedot.fi/so/1001077/cp/CadastralParcel/55804993</gml:identifier><cp:beginLifespanVersion>2017-10-19T00:00:00Z</cp:beginLifespanVersion><cp:geometry><gml:Polygon srsDimension="2" srsName="http://www.opengis.net/gml/srs/epsg.xml#3067"><gml:exterior><gml:LinearRing><gml:posList>348780.292 6994746.321 348868.203 6994592.299 348882.765 6994599.847 349068.63 6994702.553 348603.052 6995545.599 348381.724 6995476.14 348384.626 6995470.866 348780.292 6994746.321</gml:posList></gml:LinearRing></gml:exterior></gml:Polygon></cp:geometry><cp:inspireId><base:Identifier><base:localId>55804993</base:localId><base:namespace>http://paikkatiedot.fi/so/1001077/cp/CadastralParcel/</base:namespace></base:Identifier></cp:inspireId><cp:label>5-401-7-18</cp:label><cp:nationalCadastralReference>00540100070018</cp:nationalCadastralReference><cp:referencePoint><gml:Point srsDimension="2" srsName="http://www.opengis.net/gml/srs/epsg.xml#3067"><gml:pos>348644.554 6995155.265</gml:pos></gml:Point></cp:referencePoint><cp:basicPropertyUnit xlink:href="FI_CP_BASICPROPERTYUNIT_00540100070018"/></cp:CadastralParcel></wfs:member><wfs:member><cp:CadastralParcel gml:id="FI_CP_CADASTRALPARCEL_55825600"><gml:identifier codeSpace="http://paikkatiedot.fi">http://paikkatiedot.fi/so/1001077/cp/CadastralParcel/55825600</gml:identifier><cp:beginLifespanVersion>2012-09-11T00:00:00Z</cp:beginLifespanVersion><cp:geometry><gml:Polygon srsDimension="2" srsName="http://www.opengis.net/gml/srs/epsg.xml#3067"><gml:exterior><gml:LinearRing><gml:posList>349337.641 6997252.412 349330.658 6997252.353 348947.414 6997271.272 348688.161 6997281.82 348304.189 6997299.717 348105.854 6997255.855 348314.455 6996880.954 348360.387 6996799.622 348399.582 6996729.458 349337.641 6997252.412</gml:posList></gml:LinearRing></gml:exterior></gml:Polygon></cp:geometry><cp:inspireId><base:Identifier><base:localId>55825600</base:localId><base:namespace>http://paikkatiedot.fi/so/1001077/cp/CadastralParcel/</base:namespace></base:Identifier></cp:inspireId><cp:label>5-401-25-88</cp:label><cp:nationalCadastralReference>00540100250088</cp:nationalCadastralReference><cp:referencePoint><gml:Point srsDimension="2" srsName="http://www.opengis.net/gml/srs/epsg.xml#3067"><gml:pos>348623.114 6997100.23</gml:pos></gml:Point></cp:referencePoint><cp:basicPropertyUnit xlink:href="FI_CP_BASICPROPERTYUNIT_00540100250088"/></cp:CadastralParcel></wfs:member><wfs:member><cp:CadastralParcel gml:id="FI_CP_CADASTRALPARCEL_55825601"><gml:identifier codeSpace="http://paikkatiedot.fi">http://paikkatiedot.fi/so/1001077/cp/CadastralParcel/55825601</gml:identifier><cp:beginLifespanVersion>2012-09-11T00:00:00Z</cp:beginLifespanVersion><cp:geometry><gml:Polygon srsDimension="2" srsName="http://www.opengis.net/gml/srs/epsg.xml#3067"><gml:exterior><gml:LinearRing><gml:posList>348399.582 6996729.458 348538.683 6996478.579 349480.788 6997001.426 349460.138 6997035.309 349439.593 6997069.652 349419.062 6997104.057 349398.574 6997138.576 349455.268 6997171.732 349449.335 6997174.903 349439.473 6997182.263 349434.491 6997188.43 349431.068 6997195.95 349429.637 6997201.679 349425.696 6997206.204 349413.732 6997209.561 349408.112 6997215.154 349407.2 6997219.239 349407.953 6997227.474 349408.927 6997232.575 349406.155 6997236.197 349400.714 6997237.737 349395.9 6997240.903 349394.698 6997246.655 349389.741 6997252.07 349337.641 6997252.412 348399.582 6996729.458</gml:posList></gml:LinearRing></gml:exterior></gml:Polygon></cp:geometry><cp:inspireId><base:Identifier><base:localId>55825601</base:localId><base:namespace>http://paikkatiedot.fi/so/1001077/cp/CadastralParcel/</base:namespace></base:Identifier></cp:inspireId><cp:label>5-401-25-103</cp:label><cp:nationalCadastralReference>00540100250103</cp:nationalCadastralReference><cp:referencePoint><gml:Point srsDimension="2" srsName="http://www.opengis.net/gml/srs/epsg.xml#3067"><gml:pos>349016.512 6996922.888</gml:pos></gml:Point></cp:referencePoint><cp:basicPropertyUnit xlink:href="FI_CP_BASICPROPERTYUNIT_00540100250103"/></cp:CadastralParcel></wfs:member><wfs:member><cp:CadastralParcel gml:id="FI_CP_CADASTRALPARCEL_55825604"><gml:identifier codeSpace="http://paikkatiedot.fi">http://paikkatiedot.fi/so/1001077/cp/CadastralParcel/55825604</gml:identifier><cp:beginLifespanVersion>2012-09-08T00:00:00Z</cp:beginLifespanVersion><cp:geometry><gml:Polygon srsDimension="2" srsName="http://www.opengis.net/gml/srs/epsg.xml#3067"><gml:exterior><gml:LinearRing><gml:posList>348399.582 6996729.458 348360.387 6996799.622 347797.777 6996564.166 348044.319 6995970.933 348706.023 6996178.23 348617.871 6996335.928 348538.683 6996478.579 348399.582 6996729.458</gml:posList></gml:LinearRing></gml:exterior></gml:Polygon></cp:geometry><cp:inspireId><base:Identifier><base:localId>55825604</base:localId><base:namespace>http://paikkatiedot.fi/so/1001077/cp/CadastralParcel/</base:namespace></base:Identifier></cp:inspireId><cp:label>5-401-15-283</cp:label><cp:nationalCadastralReference>00540100150283</cp:nationalCadastralReference><cp:referencePoint><gml:Point srsDimension="2" srsName="http://www.opengis.net/gml/srs/epsg.xml#3067"><gml:pos>348130.088 6996366.322</gml:pos></gml:Point></cp:referencePoint><cp:basicPropertyUnit xlink:href="FI_CP_BASICPROPERTYUNIT_00540100150283"/></cp:CadastralParcel></wfs:member><wfs:member><cp:CadastralParcel gml:id="FI_CP_CADASTRALPARCEL_55825605"><gml:identifier codeSpace="http://paikkatiedot.fi">http://paikkatiedot.fi/so/1001077/cp/CadastralParcel/55825605</gml:identifier><cp:beginLifespanVersion>2012-09-11T00:00:00Z</cp:beginLifespanVersion><cp:geometry><gml:Polygon srsDimension="2" srsName="http://www.opengis.net/gml/srs/epsg.xml#3067"><gml:exterior><gml:LinearRing><gml:posList>348538.683 6996478.579 348617.871 6996335.928 349394.421 6996766.404 349565.619 6996861.306 349545.797 6996896.166 349589.848 6996920.268 349563.696 6996977.71 349523.672 6996956.186 349510.105 6997017.696 349480.788 6997001.426 348538.683 6996478.579</gml:posList></gml:LinearRing></gml:exterior></gml:Polygon></cp:geometry><cp:inspireId><base:Identifier><base:localId>55825605</base:localId><base:namespace>http://paikkatiedot.fi/so/1001077/cp/CadastralParcel/</base:namespace></base:Identifier></cp:inspireId><cp:label>5-401-15-260</cp:label><cp:nationalCadastralReference>00540100150260</cp:nationalCadastralReference><cp:referencePoint><gml:Point srsDimension="2" srsName="http://www.opengis.net/gml/srs/epsg.xml#3067"><gml:pos>348750.982 6996496.242</gml:pos></gml:Point></cp:referencePoint><cp:basicPropertyUnit xlink:href="FI_CP_BASICPROPERTYUNIT_00540100150260"/></cp:CadastralParcel></wfs:member><wfs:member><cp:CadastralParcel gml:id="FI_CP_CADASTRALPARCEL_55825606"><gml:identifier codeSpace="http://paikkatiedot.fi">http://paikkatiedot.fi/so/1001077/cp/CadastralParcel/55825606</gml:identifier><cp:beginLifespanVersion>2012-09-08T00:00:00Z</cp:beginLifespanVersion><cp:geometry><gml:Polygon srsDimension="2" srsName="http://www.opengis.net/gml/srs/epsg.xml#3067"><gml:exterior><gml:LinearRing><gml:posList>349613.237 6996658.941 349690.43 6996703.169 349680.274 6996711.118 349676.485 6996717.917 349674.581 6996722.509 349674.287 6996727.557 349674.538 6996735.758 349673.171 6996743.372 349672.082 6996751.237 349670.842 6996754.474 349670.24 6996758.608 349670.619 6996763.888 349668.396 6996773 349667.859 6996775.673 349666.011 6996782.913 349664.992 6996789.451 349664.378 6996793.32 349662.575 6996797.246 349659.753 6996803.471 349655.645 6996809.094 349652.682 6996813.736 349650.199 6996817.296 349645.577 6996820.425 349639.4 6996824.291 349637.338 6996828.36 349634.929 6996833.506 349631.343 6996840.738 349589.766 6996817.671 349565.619 6996861.306 349394.421 6996766.404 348617.871 6996335.928 348706.023 6996178.23 348715.439 6996161.386 349467.619 6996578.121 349613.237 6996658.941</gml:posList></gml:LinearRing></gml:exterior></gml:Polygon></cp:geometry><cp:inspireId><base:Identifier><base:localId>55825606</base:localId><base:namespace>http://paikkatiedot.fi/so/1001077/cp/CadastralParcel/</base:namespace></base:Identifier></cp:inspireId><cp:label>5-401-15-171</cp:label><cp:nationalCadastralReference>00540100150171</cp:nationalCadastralReference><cp:referencePoint><gml:Point srsDimension="2" srsName="http://www.opengis.net/gml/srs/epsg.xml#3067"><gml:pos>349103.256 6996494.596</gml:pos></gml:Point></cp:referencePoint><cp:basicPropertyUnit xlink:href="FI_CP_BASICPROPERTYUNIT_00540100150171"/></cp:CadastralParcel></wfs:member><wfs:member><cp:CadastralParcel gml:id="FI_CP_CADASTRALPARCEL_55825612"><gml:identifier codeSpace="http://paikkatiedot.fi">http://paikkatiedot.fi/so/1001077/cp/CadastralParcel/55825612</gml:identifier><cp:beginLifespanVersion>2019-11-07T01:00:00Z</cp:beginLifespanVersion><cp:geometry><gml:Polygon srsDimension="2" srsName="http://www.opengis.net/gml/srs/epsg.xml#3067"><gml:exterior><gml:LinearRing><gml:posList>348044.319 6995970.933 348094.011 6995851.364 347950.152 6995937.315 347427.679 6995779.019 347504.299 6995535.101 348833.92 6995948.918 348803.891 6996003.152 348794.745 6996019.513 348715.439 6996161.386 348706.023 6996178.23 348044.319 6995970.933</gml:posList></gml:LinearRing></gml:exterior></gml:Polygon></cp:geometry><cp:inspireId><base:Identifier><base:localId>55825612</base:localId><base:namespace>http://paikkatiedot.fi/so/1001077/cp/CadastralParcel/</base:namespace></base:Identifier></cp:inspireId><cp:label>5-401-9-99</cp:label><cp:nationalCadastralReference>00540100090099</cp:nationalCadastralReference><cp:referencePoint><gml:Point srsDimension="2" srsName="http://www.opengis.net/gml/srs/epsg.xml#3067"><gml:pos>348487.484 6996043.267</gml:pos></gml:Point></cp:referencePoint><cp:basicPropertyUnit xlink:href="FI_CP_BASICPROPERTYUNIT_00540100090099"/></cp:CadastralParcel></wfs:member><wfs:member><cp:CadastralParcel gml:id="FI_CP_CADASTRALPARCEL_55825613"><gml:identifier codeSpace="http://paikkatiedot.fi">http://paikkatiedot.fi/so/1001077/cp/CadastralParcel/55825613</gml:identifier><cp:beginLifespanVersion>2020-02-22T01:00:00Z</cp:beginLifespanVersion><cp:geometry><gml:Polygon srsDimension="2" srsName="http://www.opengis.net/gml/srs/epsg.xml#3067"><gml:exterior><gml:LinearRing><gml:posList>347504.299 6995535.101 347598.91 6995230.075 347601.309 6995222.339 347698.131 6995254.388 347849.97 6995303.471 348162.769 6995404.586 348381.724 6995476.14 348603.052 6995545.599 348796.906 6995607.763 348892.253 6995639.272 348988.306 6995670.096 348910.139 6995812.853 348833.92 6995948.918 347504.299 6995535.101</gml:posList></gml:LinearRing></gml:exterior></gml:Polygon></cp:geometry><cp:inspireId><base:Identifier><base:localId>55825613</base:localId><base:namespace>http://paikkatiedot.fi/so/1001077/cp/CadastralParcel/</base:namespace></base:Identifier></cp:inspireId><cp:label>5-401-15-233</cp:label><cp:nationalCadastralReference>00540100150233</cp:nationalCadastralReference><cp:referencePoint><gml:Point srsDimension="2" srsName="http://www.opengis.net/gml/srs/epsg.xml#3067"><gml:pos>347956.945 6995524.018</gml:pos></gml:Point></cp:referencePoint><cp:basicPropertyUnit xlink:href="FI_CP_BASICPROPERTYUNIT_00540100150233"/></cp:CadastralParcel></wfs:member><wfs:member><cp:CadastralParcel gml:id="FI_CP_CADASTRALPARCEL_55825614"><gml:identifier codeSpace="http://paikkatiedot.fi">http://paikkatiedot.fi/so/1001077/cp/CadastralParcel/55825614</gml:identifier><cp:beginLifespanVersion>2017-10-19T00:00:00Z</cp:beginLifespanVersion><cp:geometry><gml:Polygon srsDimension="2" srsName="http://www.opengis.net/gml/srs/epsg.xml#3067"><gml:exterior><gml:LinearRing><gml:posList>349068.63 6994702.553 349209.872 6994780.824 349243.642 6994799.304 348796.906 6995607.763 348603.052 6995545.599 349068.63 6994702.553</gml:posList></gml:LinearRing></gml:exterior></gml:Polygon></cp:geometry><cp:inspireId><base:Identifier><base:localId>55825614</base:localId><base:namespace>http://paikkatiedot.fi/so/1001077/cp/CadastralParcel/</base:namespace></base:Identifier></cp:inspireId><cp:label>5-401-10-118</cp:label><cp:nationalCadastralReference>00540100100118</cp:nationalCadastralReference><cp:referencePoint><gml:Point srsDimension="2" srsName="http://www.opengis.net/gml/srs/epsg.xml#3067"><gml:pos>349052.316 6994800.474</gml:pos></gml:Point></cp:referencePoint><cp:basicPropertyUnit xlink:href="FI_CP_BASICPROPERTYUNIT_00540100100118"/></cp:CadastralParcel></wfs:member></wfs:FeatureCollection>